{
"meta":{"test_sets":[],"test_metrics":[],"learn_metrics":[{"best_value":"Min","name":"RMSE"}],"launch_mode":"Train","parameters":"","iteration_count":1000,"learn_sets":["learn"],"name":"experiment"},
"iterations":[
{"learn":[135.1478617],"iteration":0,"passed_time":0.002774953246,"remaining_time":2.772178292},
{"learn":[132.7993502],"iteration":1,"passed_time":0.004690080992,"remaining_time":2.340350415},
{"learn":[130.6317313],"iteration":2,"passed_time":0.006531116671,"remaining_time":2.170507774},
{"learn":[128.716544],"iteration":3,"passed_time":0.008404286823,"remaining_time":2.092667419},
{"learn":[127.0496127],"iteration":4,"passed_time":0.01091495018,"remaining_time":2.172075086},
{"learn":[125.2244554],"iteration":5,"passed_time":0.01274658121,"remaining_time":2.111683621},
{"learn":[123.5433602],"iteration":6,"passed_time":0.01452890032,"remaining_time":2.061028288},
{"learn":[121.8888182],"iteration":7,"passed_time":0.01646867462,"remaining_time":2.042115653},
{"learn":[120.2878802],"iteration":8,"passed_time":0.01837381614,"remaining_time":2.02316131},
{"learn":[118.9332961],"iteration":9,"passed_time":0.02016237032,"remaining_time":1.996074662},
{"learn":[117.6667872],"iteration":10,"passed_time":0.02274597733,"remaining_time":2.045070144},
{"learn":[116.2767821],"iteration":11,"passed_time":0.02454601415,"remaining_time":2.020955165},
{"learn":[115.0386441],"iteration":12,"passed_time":0.02640226738,"remaining_time":2.004541377},
{"learn":[113.760258],"iteration":13,"passed_time":0.02828240143,"remaining_time":1.99188913},
{"learn":[112.6688633],"iteration":14,"passed_time":0.03011159726,"remaining_time":1.97732822},
{"learn":[111.4147937],"iteration":15,"passed_time":0.03194297034,"remaining_time":1.964492676},
{"learn":[110.48405],"iteration":16,"passed_time":0.03373185038,"remaining_time":1.950494642},
{"learn":[109.3497889],"iteration":17,"passed_time":0.0355863618,"remaining_time":1.941433738},
{"learn":[108.2375275],"iteration":18,"passed_time":0.03739904885,"remaining_time":1.930971943},
{"learn":[107.3960673],"iteration":19,"passed_time":0.03922333367,"remaining_time":1.92194335},
{"learn":[106.5423821],"iteration":20,"passed_time":0.04099455283,"remaining_time":1.91112701},
{"learn":[105.648384],"iteration":21,"passed_time":0.04325552573,"remaining_time":1.922904735},
{"learn":[104.6136634],"iteration":22,"passed_time":0.04524722651,"remaining_time":1.922023491},
{"learn":[103.8343124],"iteration":23,"passed_time":0.04703038847,"remaining_time":1.912569131},
{"learn":[103.206049],"iteration":24,"passed_time":0.04879054827,"remaining_time":1.902831382},
{"learn":[102.4141107],"iteration":25,"passed_time":0.0506094191,"remaining_time":1.8959067},
{"learn":[101.7482876],"iteration":26,"passed_time":0.05251282286,"remaining_time":1.892406542},
{"learn":[101.1696838],"iteration":27,"passed_time":0.05435477484,"remaining_time":1.886887184},
{"learn":[100.2633574],"iteration":28,"passed_time":0.05860929771,"remaining_time":1.962400968},
{"learn":[99.68006782],"iteration":29,"passed_time":0.06113610192,"remaining_time":1.976733962},
{"learn":[99.03603289],"iteration":30,"passed_time":0.06312582915,"remaining_time":1.97319124},
{"learn":[98.56192637],"iteration":31,"passed_time":0.06637414988,"remaining_time":2.007818034},
{"learn":[97.83099124],"iteration":32,"passed_time":0.06890033597,"remaining_time":2.018988633},
{"learn":[97.27777602],"iteration":33,"passed_time":0.07120639471,"remaining_time":2.023099332},
{"learn":[96.75610377],"iteration":34,"passed_time":0.07311297395,"remaining_time":2.015829139},
{"learn":[96.3549505],"iteration":35,"passed_time":0.07493991982,"remaining_time":2.00672452},
{"learn":[95.91476414],"iteration":36,"passed_time":0.07738896089,"remaining_time":2.014204577},
{"learn":[95.3350724],"iteration":37,"passed_time":0.07930343546,"remaining_time":2.007629077},
{"learn":[94.83115467],"iteration":38,"passed_time":0.081354961,"remaining_time":2.00466968},
{"learn":[94.4007046],"iteration":39,"passed_time":0.08334190576,"remaining_time":2.000205738},
{"learn":[93.81665913],"iteration":40,"passed_time":0.08598625715,"remaining_time":2.011239527},
{"learn":[93.22625615],"iteration":41,"passed_time":0.08796686167,"remaining_time":2.006482226},
{"learn":[92.7731375],"iteration":42,"passed_time":0.08988203739,"remaining_time":2.000397902},
{"learn":[92.33418743],"iteration":43,"passed_time":0.0918016322,"remaining_time":1.9945991},
{"learn":[91.95480093],"iteration":44,"passed_time":0.0938658327,"remaining_time":1.992041561},
{"learn":[91.58108582],"iteration":45,"passed_time":0.09744332116,"remaining_time":2.020889748},
{"learn":[91.29288769],"iteration":46,"passed_time":0.09927765163,"remaining_time":2.013012809},
{"learn":[90.80580673],"iteration":47,"passed_time":0.101802417,"remaining_time":2.01908127},
{"learn":[90.59407971],"iteration":48,"passed_time":0.1041281205,"remaining_time":2.020935563},
{"learn":[90.28789404],"iteration":49,"passed_time":0.1065437255,"remaining_time":2.024330785},
{"learn":[89.97805611],"iteration":50,"passed_time":0.1096652509,"remaining_time":2.040633786},
{"learn":[89.72163907],"iteration":51,"passed_time":0.1121021045,"remaining_time":2.043707597},
{"learn":[89.26386809],"iteration":52,"passed_time":0.1145612643,"remaining_time":2.046972024},
{"learn":[88.98608012],"iteration":53,"passed_time":0.1166616969,"remaining_time":2.043740098},
{"learn":[88.75888275],"iteration":54,"passed_time":0.1195661833,"remaining_time":2.054364422},
{"learn":[88.41604326],"iteration":55,"passed_time":0.1220847678,"remaining_time":2.058000372},
{"learn":[88.25897361],"iteration":56,"passed_time":0.1241459065,"remaining_time":2.053852453},
{"learn":[88.02639692],"iteration":57,"passed_time":0.1264378278,"remaining_time":2.053524721},
{"learn":[87.7761664],"iteration":58,"passed_time":0.1286203486,"remaining_time":2.05138556},
{"learn":[87.53553653],"iteration":59,"passed_time":0.1318718345,"remaining_time":2.065992074},
{"learn":[87.0693161],"iteration":60,"passed_time":0.1343952189,"remaining_time":2.068805091},
{"learn":[86.81040754],"iteration":61,"passed_time":0.1367990561,"remaining_time":2.069637332},
{"learn":[86.72985304],"iteration":62,"passed_time":0.138261322,"remaining_time":2.056362837},
{"learn":[86.53516423],"iteration":63,"passed_time":0.1429529197,"remaining_time":2.090686451},
{"learn":[86.16273563],"iteration":64,"passed_time":0.1460433103,"remaining_time":2.100776849},
{"learn":[85.97622064],"iteration":65,"passed_time":0.1478705891,"remaining_time":2.092592882},
{"learn":[85.78937376],"iteration":66,"passed_time":0.149542402,"remaining_time":2.082433748},
{"learn":[85.66395784],"iteration":67,"passed_time":0.1511541559,"remaining_time":2.071701078},
{"learn":[85.29551018],"iteration":68,"passed_time":0.1542741705,"remaining_time":2.081583373},
{"learn":[84.98077478],"iteration":69,"passed_time":0.1559546349,"remaining_time":2.071968721},
{"learn":[84.66371698],"iteration":70,"passed_time":0.1578070429,"remaining_time":2.064827364},
{"learn":[84.39708643],"iteration":71,"passed_time":0.1594604573,"remaining_time":2.055268116},
{"learn":[84.24543594],"iteration":72,"passed_time":0.161050519,"remaining_time":2.045120975},
{"learn":[84.11388922],"iteration":73,"passed_time":0.1626672762,"remaining_time":2.035539159},
{"learn":[83.9588361],"iteration":74,"passed_time":0.1645999987,"remaining_time":2.030066651},
{"learn":[83.61644668],"iteration":75,"passed_time":0.1662061611,"remaining_time":2.020717012},
{"learn":[83.51665494],"iteration":76,"passed_time":0.168344774,"remaining_time":2.017950992},
{"learn":[83.25279977],"iteration":77,"passed_time":0.169955626,"remaining_time":2.008962656},
{"learn":[83.14199948],"iteration":78,"passed_time":0.1715131064,"remaining_time":1.999538873},
{"learn":[82.88937907],"iteration":79,"passed_time":0.1731073123,"remaining_time":1.990734091},
{"learn":[82.73981885],"iteration":80,"passed_time":0.1754848832,"remaining_time":1.990995156},
{"learn":[82.6327745],"iteration":81,"passed_time":0.1771188156,"remaining_time":1.98286674},
{"learn":[82.4963103],"iteration":82,"passed_time":0.178702012,"remaining_time":1.974334277},
{"learn":[82.40136904],"iteration":83,"passed_time":0.1812114645,"remaining_time":1.976067875},
{"learn":[82.24036027],"iteration":84,"passed_time":0.1831327768,"remaining_time":1.97137048},
{"learn":[82.06067292],"iteration":85,"passed_time":0.1851802445,"remaining_time":1.968078413},
{"learn":[81.97070493],"iteration":86,"passed_time":0.1873083062,"remaining_time":1.965660731},
{"learn":[81.88882657],"iteration":87,"passed_time":0.1891591731,"remaining_time":1.960376885},
{"learn":[81.80056527],"iteration":88,"passed_time":0.1909339943,"remaining_time":1.954391785},
{"learn":[81.72326775],"iteration":89,"passed_time":0.1928222946,"remaining_time":1.949647645},
{"learn":[81.57675407],"iteration":90,"passed_time":0.1945970959,"remaining_time":1.943832529},
{"learn":[81.43764447],"iteration":91,"passed_time":0.1981506138,"remaining_time":1.955660406},
{"learn":[81.3757042],"iteration":92,"passed_time":0.2000860454,"remaining_time":1.951376809},
{"learn":[81.1457485],"iteration":93,"passed_time":0.2018623254,"remaining_time":1.945609222},
{"learn":[80.99804969],"iteration":94,"passed_time":0.2036993158,"remaining_time":1.940504009},
{"learn":[80.87565406],"iteration":95,"passed_time":0.2054612687,"remaining_time":1.934760281},
{"learn":[80.795009],"iteration":96,"passed_time":0.2075979357,"remaining_time":1.932586969},
{"learn":[80.65162855],"iteration":97,"passed_time":0.2094227313,"remaining_time":1.927543914},
{"learn":[80.57533791],"iteration":98,"passed_time":0.211102096,"remaining_time":1.921242308},
{"learn":[80.42464119],"iteration":99,"passed_time":0.2129902346,"remaining_time":1.916912112},
{"learn":[80.32026276],"iteration":100,"passed_time":0.2147811258,"remaining_time":1.911764675},
{"learn":[80.26006417],"iteration":101,"passed_time":0.2167481587,"remaining_time":1.908233789},
{"learn":[80.1899332],"iteration":102,"passed_time":0.2200672244,"remaining_time":1.91650777},
{"learn":[80.14954576],"iteration":103,"passed_time":0.2219089992,"remaining_time":1.911831378},
{"learn":[80.09092271],"iteration":104,"passed_time":0.2238522608,"remaining_time":1.908074033},
{"learn":[79.97501709],"iteration":105,"passed_time":0.2256220688,"remaining_time":1.902888015},
{"learn":[79.86217319],"iteration":106,"passed_time":0.2276567775,"remaining_time":1.899976657},
{"learn":[79.83262953],"iteration":107,"passed_time":0.2288440411,"remaining_time":1.890082265},
{"learn":[79.77673045],"iteration":108,"passed_time":0.230577439,"remaining_time":1.88481191},
{"learn":[79.7199612],"iteration":109,"passed_time":0.2324129567,"remaining_time":1.880432104},
{"learn":[79.65714795],"iteration":110,"passed_time":0.2341393232,"remaining_time":1.875223949},
{"learn":[79.58393533],"iteration":111,"passed_time":0.2358586251,"remaining_time":1.870021956},
{"learn":[79.47570875],"iteration":112,"passed_time":0.2380074405,"remaining_time":1.868253095},
{"learn":[79.37646253],"iteration":113,"passed_time":0.2417174486,"remaining_time":1.878611048},
{"learn":[79.30490767],"iteration":114,"passed_time":0.2439529251,"remaining_time":1.877376858},
{"learn":[79.15113541],"iteration":115,"passed_time":0.2457676916,"remaining_time":1.872919305},
{"learn":[79.03586993],"iteration":116,"passed_time":0.247569216,"remaining_time":1.868406989},
{"learn":[78.96043125],"iteration":117,"passed_time":0.2493268048,"remaining_time":1.863612219},
{"learn":[78.8821507],"iteration":118,"passed_time":0.251125471,"remaining_time":1.859172605},
{"learn":[78.86494503],"iteration":119,"passed_time":0.2520039279,"remaining_time":1.848028805},
{"learn":[78.78893709],"iteration":120,"passed_time":0.2538073166,"remaining_time":1.843773812},
{"learn":[78.67384523],"iteration":121,"passed_time":0.256126988,"remaining_time":1.843274553},
{"learn":[78.63104479],"iteration":122,"passed_time":0.2646390716,"remaining_time":1.886898096},
{"learn":[78.56404643],"iteration":123,"passed_time":0.2662096609,"remaining_time":1.880642443},
{"learn":[78.51203685],"iteration":124,"passed_time":0.2678093424,"remaining_time":1.874665397},
{"learn":[78.34169719],"iteration":125,"passed_time":0.2697288328,"remaining_time":1.87097619},
{"learn":[78.05174273],"iteration":126,"passed_time":0.2713798231,"remaining_time":1.865469178},
{"learn":[77.93278624],"iteration":127,"passed_time":0.2742807078,"remaining_time":1.868537322},
{"learn":[77.84236221],"iteration":128,"passed_time":0.2758494243,"remaining_time":1.862518206},
{"learn":[77.69296782],"iteration":129,"passed_time":0.2774592504,"remaining_time":1.856842676},
{"learn":[77.62728344],"iteration":130,"passed_time":0.2792918021,"remaining_time":1.852706687},
{"learn":[77.50367845],"iteration":131,"passed_time":0.2809342099,"remaining_time":1.847355259},
{"learn":[77.46007518],"iteration":132,"passed_time":0.2825792345,"remaining_time":1.842076664},
{"learn":[77.37564632],"iteration":133,"passed_time":0.2852989323,"remaining_time":1.843797577},
{"learn":[77.27809338],"iteration":134,"passed_time":0.2869237324,"remaining_time":1.838437248},
{"learn":[77.1499771],"iteration":135,"passed_time":0.288519662,"remaining_time":1.832948441},
{"learn":[77.08997221],"iteration":136,"passed_time":0.2902445436,"remaining_time":1.828328767},
{"learn":[77.00087099],"iteration":137,"passed_time":0.2918847062,"remaining_time":1.823221861},
{"learn":[76.96719554],"iteration":138,"passed_time":0.2930099608,"remaining_time":1.814975369},
{"learn":[76.93630905],"iteration":139,"passed_time":0.2946559733,"remaining_time":1.81002955},
{"learn":[76.7216891],"iteration":140,"passed_time":0.2962451505,"remaining_time":1.804784285},
{"learn":[76.67308234],"iteration":141,"passed_time":0.2978134308,"remaining_time":1.799464251},
{"learn":[76.58993895],"iteration":142,"passed_time":0.2994566933,"remaining_time":1.794646057},
{"learn":[76.52125237],"iteration":143,"passed_time":0.3010936683,"remaining_time":1.789834584},
{"learn":[76.34748964],"iteration":144,"passed_time":0.3026979409,"remaining_time":1.784874065},
{"learn":[76.03323232],"iteration":145,"passed_time":0.3048640743,"remaining_time":1.783246023},
{"learn":[75.94753761],"iteration":146,"passed_time":0.3068395327,"remaining_time":1.780504227},
{"learn":[75.86161513],"iteration":147,"passed_time":0.3091199024,"remaining_time":1.779528087},
{"learn":[75.81534851],"iteration":148,"passed_time":0.3108252499,"remaining_time":1.775250253},
{"learn":[75.74950729],"iteration":149,"passed_time":0.3126015853,"remaining_time":1.771408983},
{"learn":[75.71308826],"iteration":150,"passed_time":0.3145100646,"remaining_time":1.768338045},
{"learn":[75.64614601],"iteration":151,"passed_time":0.3164193031,"remaining_time":1.765286638},
{"learn":[75.43437248],"iteration":152,"passed_time":0.3182660387,"remaining_time":1.761904149},
{"learn":[75.37090796],"iteration":153,"passed_time":0.320126231,"remaining_time":1.758615528},
{"learn":[75.32266421],"iteration":154,"passed_time":0.3219855718,"remaining_time":1.755340698},
{"learn":[75.29349406],"iteration":155,"passed_time":0.3237844045,"remaining_time":1.75175665},
{"learn":[75.23383064],"iteration":156,"passed_time":0.3264419427,"remaining_time":1.7528061},
{"learn":[75.18975396],"iteration":157,"passed_time":0.3282509867,"remaining_time":1.749286904},
{"learn":[75.11539934],"iteration":158,"passed_time":0.3300783714,"remaining_time":1.745886228},
{"learn":[75.00604139],"iteration":159,"passed_time":0.3320206174,"remaining_time":1.743108241},
{"learn":[74.89718489],"iteration":160,"passed_time":0.3339150033,"remaining_time":1.740091228},
{"learn":[74.75395516],"iteration":161,"passed_time":0.3357251422,"remaining_time":1.736652279},
{"learn":[74.7204811],"iteration":162,"passed_time":0.3376310956,"remaining_time":1.733725319},
{"learn":[74.68807122],"iteration":163,"passed_time":0.3394067427,"remaining_time":1.730146566},
{"learn":[74.61640763],"iteration":164,"passed_time":0.3413958271,"remaining_time":1.727669791},
{"learn":[74.5736463],"iteration":165,"passed_time":0.3431092326,"remaining_time":1.723813856},
{"learn":[74.53511659],"iteration":166,"passed_time":0.3448016402,"remaining_time":1.71987884},
{"learn":[74.47468083],"iteration":167,"passed_time":0.3484650872,"remaining_time":1.72573186},
{"learn":[74.42371781],"iteration":168,"passed_time":0.3503902432,"remaining_time":1.722924806},
{"learn":[74.40264553],"iteration":169,"passed_time":0.3522895427,"remaining_time":1.720001885},
{"learn":[74.36341679],"iteration":170,"passed_time":0.3541614833,"remaining_time":1.716958302},
{"learn":[74.28154273],"iteration":171,"passed_time":0.355996041,"remaining_time":1.713748384},
{"learn":[74.09984909],"iteration":172,"passed_time":0.3589486168,"remaining_time":1.715898879},
{"learn":[74.06383729],"iteration":173,"passed_time":0.3607497828,"remaining_time":1.712524831},
{"learn":[74.0176131],"iteration":174,"passed_time":0.3625723742,"remaining_time":1.709269764},
{"learn":[73.89421703],"iteration":175,"passed_time":0.3644264018,"remaining_time":1.706178154},
{"learn":[73.82509341],"iteration":176,"passed_time":0.3662897009,"remaining_time":1.703143637},
{"learn":[73.78863654],"iteration":177,"passed_time":0.368114744,"remaining_time":1.699945616},
{"learn":[73.74737499],"iteration":178,"passed_time":0.3701179094,"remaining_time":1.697579908},
{"learn":[73.70339074],"iteration":179,"passed_time":0.3720906038,"remaining_time":1.695079417},
{"learn":[73.60288779],"iteration":180,"passed_time":0.3739924813,"remaining_time":1.692264321},
{"learn":[73.56743385],"iteration":181,"passed_time":0.3759024257,"remaining_time":1.689495518},
{"learn":[73.51599612],"iteration":182,"passed_time":0.3781651651,"remaining_time":1.688311147},
{"learn":[73.51379494],"iteration":183,"passed_time":0.3789559867,"remaining_time":1.680587419},
{"learn":[73.43091054],"iteration":184,"passed_time":0.3808888045,"remaining_time":1.677969598},
{"learn":[73.35428118],"iteration":185,"passed_time":0.3840118329,"remaining_time":1.680567914},
{"learn":[73.31425795],"iteration":186,"passed_time":0.3898100283,"remaining_time":1.694735577},
{"learn":[73.26527857],"iteration":187,"passed_time":0.3922235553,"remaining_time":1.694071952},
{"learn":[73.23074185],"iteration":188,"passed_time":0.4009463,"remaining_time":1.720462695},
{"learn":[73.20103892],"iteration":189,"passed_time":0.4054207317,"remaining_time":1.728372593},
{"learn":[73.14428018],"iteration":190,"passed_time":0.4080255157,"remaining_time":1.728233729},
{"learn":[73.06961195],"iteration":191,"passed_time":0.410005408,"remaining_time":1.725439425},
{"learn":[73.02640772],"iteration":192,"passed_time":0.4122357499,"remaining_time":1.723700778},
{"learn":[72.96346779],"iteration":193,"passed_time":0.4139351568,"remaining_time":1.719751218},
{"learn":[72.91762645],"iteration":194,"passed_time":0.4159327376,"remaining_time":1.717055661},
{"learn":[72.75808062],"iteration":195,"passed_time":0.4176104846,"remaining_time":1.713055253},
{"learn":[72.69343945],"iteration":196,"passed_time":0.4193007795,"remaining_time":1.709129573},
{"learn":[72.50815349],"iteration":197,"passed_time":0.420904045,"remaining_time":1.70487396},
{"learn":[72.44429015],"iteration":198,"passed_time":0.4225336671,"remaining_time":1.700751092},
{"learn":[72.29156425],"iteration":199,"passed_time":0.4241592573,"remaining_time":1.696637029},
{"learn":[72.23605065],"iteration":200,"passed_time":0.4270325857,"remaining_time":1.697507642},
{"learn":[72.19321246],"iteration":201,"passed_time":0.4288163743,"remaining_time":1.694036964},
{"learn":[72.11483484],"iteration":202,"passed_time":0.4306923125,"remaining_time":1.690944695},
{"learn":[72.06768842],"iteration":203,"passed_time":0.432539264,"remaining_time":1.687751246},
{"learn":[71.92091257],"iteration":204,"passed_time":0.4344164964,"remaining_time":1.684688364},
{"learn":[71.90700294],"iteration":205,"passed_time":0.4376632436,"remaining_time":1.686915609},
{"learn":[71.69840016],"iteration":206,"passed_time":0.4395326257,"remaining_time":1.683813392},
{"learn":[71.63843021],"iteration":207,"passed_time":0.4413230649,"remaining_time":1.680422439},
{"learn":[71.61816516],"iteration":208,"passed_time":0.4429662174,"remaining_time":1.676489368},
{"learn":[71.58563117],"iteration":209,"passed_time":0.4448467374,"remaining_time":1.67347106},
{"learn":[71.51178387],"iteration":210,"passed_time":0.4468186839,"remaining_time":1.67080541},
{"learn":[71.49205856],"iteration":211,"passed_time":0.449141596,"remaining_time":1.669450838},
{"learn":[71.44629072],"iteration":212,"passed_time":0.4510808257,"remaining_time":1.66666953},
{"learn":[71.43240515],"iteration":213,"passed_time":0.4528088085,"remaining_time":1.663120203},
{"learn":[71.38110884],"iteration":214,"passed_time":0.4546957873,"remaining_time":1.66016834},
{"learn":[71.28674337],"iteration":215,"passed_time":0.4565556013,"remaining_time":1.657127738},
{"learn":[71.14658945],"iteration":216,"passed_time":0.4591600254,"remaining_time":1.656784792},
{"learn":[71.05805712],"iteration":217,"passed_time":0.4608889733,"remaining_time":1.653280629},
{"learn":[71.03968517],"iteration":218,"passed_time":0.4626436199,"remaining_time":1.649884325},
{"learn":[70.97157639],"iteration":219,"passed_time":0.4645228196,"remaining_time":1.646944542},
{"learn":[70.92327019],"iteration":220,"passed_time":0.4662391755,"remaining_time":1.643440352},
{"learn":[70.83946679],"iteration":221,"passed_time":0.468953904,"remaining_time":1.643451069},
{"learn":[70.79907357],"iteration":222,"passed_time":0.4714834973,"remaining_time":1.642792275},
{"learn":[70.77345018],"iteration":223,"passed_time":0.4734283025,"remaining_time":1.640090905},
{"learn":[70.706879],"iteration":224,"passed_time":0.4751975086,"remaining_time":1.636791419},
{"learn":[70.67441145],"iteration":225,"passed_time":0.4770309029,"remaining_time":1.633725305},
{"learn":[70.5265883],"iteration":226,"passed_time":0.479305704,"remaining_time":1.632173168},
{"learn":[70.46262124],"iteration":227,"passed_time":0.4811647241,"remaining_time":1.629206873},
{"learn":[70.39784294],"iteration":228,"passed_time":0.482876875,"remaining_time":1.625755767},
{"learn":[70.33750166],"iteration":229,"passed_time":0.4847391751,"remaining_time":1.622822456},
{"learn":[70.28134137],"iteration":230,"passed_time":0.4863675814,"remaining_time":1.619119784},
{"learn":[70.16669317],"iteration":231,"passed_time":0.4881412748,"remaining_time":1.615915944},
{"learn":[70.12621796],"iteration":232,"passed_time":0.4899771737,"remaining_time":1.612929151},
{"learn":[70.07805598],"iteration":233,"passed_time":0.4917974007,"remaining_time":1.609900893},
{"learn":[69.96455943],"iteration":234,"passed_time":0.4935497744,"remaining_time":1.606662031},
{"learn":[69.91087159],"iteration":235,"passed_time":0.4953794636,"remaining_time":1.60368606},
{"learn":[69.88764602],"iteration":236,"passed_time":0.4972788357,"remaining_time":1.6009441},
{"learn":[69.83140491],"iteration":237,"passed_time":0.5008436448,"remaining_time":1.603541417},
{"learn":[69.68489412],"iteration":238,"passed_time":0.5026966738,"remaining_time":1.60063669},
{"learn":[69.60037257],"iteration":239,"passed_time":0.5044064028,"remaining_time":1.597286942},
{"learn":[69.51572657],"iteration":240,"passed_time":0.5063245824,"remaining_time":1.594607295},
{"learn":[69.46133061],"iteration":241,"passed_time":0.509271046,"remaining_time":1.595154764},
{"learn":[69.38288393],"iteration":242,"passed_time":0.5131516267,"remaining_time":1.598583463},
{"learn":[69.33077191],"iteration":243,"passed_time":0.515120542,"remaining_time":1.59602922},
{"learn":[69.25224968],"iteration":244,"passed_time":0.5168217808,"remaining_time":1.592654875},
{"learn":[69.16896249],"iteration":245,"passed_time":0.5184820055,"remaining_time":1.589168424},
{"learn":[69.10264646],"iteration":246,"passed_time":0.5217183211,"remaining_time":1.590501602},
{"learn":[69.01689725],"iteration":247,"passed_time":0.5233435264,"remaining_time":1.586912628},
{"learn":[68.96701285],"iteration":248,"passed_time":0.5249330261,"remaining_time":1.583231737},
{"learn":[68.91153389],"iteration":249,"passed_time":0.5265939443,"remaining_time":1.579781833},
{"learn":[68.81066339],"iteration":250,"passed_time":0.5284377857,"remaining_time":1.576892038},
{"learn":[68.69714419],"iteration":251,"passed_time":0.5300471501,"remaining_time":1.573314557},
{"learn":[68.62438713],"iteration":252,"passed_time":0.532443699,"remaining_time":1.57207685},
{"learn":[68.55902759],"iteration":253,"passed_time":0.5340815379,"remaining_time":1.568601682},
{"learn":[68.50194509],"iteration":254,"passed_time":0.5356529523,"remaining_time":1.564946861},
{"learn":[68.41479502],"iteration":255,"passed_time":0.5372634002,"remaining_time":1.561421757},
{"learn":[68.38082651],"iteration":256,"passed_time":0.539363214,"remaining_time":1.559326335},
{"learn":[68.32878029],"iteration":257,"passed_time":0.5409720946,"remaining_time":1.55581897},
{"learn":[68.21754464],"iteration":258,"passed_time":0.5434620091,"remaining_time":1.554846906},
{"learn":[68.1684245],"iteration":259,"passed_time":0.5450645332,"remaining_time":1.551337518},
{"learn":[68.11171614],"iteration":260,"passed_time":0.5493438318,"remaining_time":1.555421807},
{"learn":[68.07659536],"iteration":261,"passed_time":0.551330567,"remaining_time":1.552984574},
{"learn":[67.96732929],"iteration":262,"passed_time":0.5531662868,"remaining_time":1.550127579},
{"learn":[67.89315783],"iteration":263,"passed_time":0.5553409809,"remaining_time":1.548223341},
{"learn":[67.82560125],"iteration":264,"passed_time":0.5570658278,"remaining_time":1.545069371},
{"learn":[67.78021472],"iteration":265,"passed_time":0.559310417,"remaining_time":1.543360324},
{"learn":[67.72452892],"iteration":266,"passed_time":0.5615540435,"remaining_time":1.541644621},
{"learn":[67.62995394],"iteration":267,"passed_time":0.5633853881,"remaining_time":1.538798896},
{"learn":[67.55937293],"iteration":268,"passed_time":0.5669145444,"remaining_time":1.540574468},
{"learn":[67.46178643],"iteration":269,"passed_time":0.5689008929,"remaining_time":1.538139451},
{"learn":[67.32469683],"iteration":270,"passed_time":0.5712267484,"remaining_time":1.536621032},
{"learn":[67.26727117],"iteration":271,"passed_time":0.5734497676,"remaining_time":1.534821437},
{"learn":[67.20875597],"iteration":272,"passed_time":0.575942028,"remaining_time":1.53373573},
{"learn":[67.16576283],"iteration":273,"passed_time":0.5784303918,"remaining_time":1.532629432},
{"learn":[67.08714994],"iteration":274,"passed_time":0.5807315222,"remaining_time":1.531019468},
{"learn":[66.92938075],"iteration":275,"passed_time":0.5832511315,"remaining_time":1.529977606},
{"learn":[66.89134254],"iteration":276,"passed_time":0.5858182068,"remaining_time":1.529048966},
{"learn":[66.81040125],"iteration":277,"passed_time":0.5884069511,"remaining_time":1.528164815},
{"learn":[66.74466087],"iteration":278,"passed_time":0.5903694165,"remaining_time":1.525649997},
{"learn":[66.71183981],"iteration":279,"passed_time":0.5925761122,"remaining_time":1.523767146},
{"learn":[66.61231069],"iteration":280,"passed_time":0.5943595572,"remaining_time":1.520799009},
{"learn":[66.52149407],"iteration":281,"passed_time":0.5962224012,"remaining_time":1.518041433},
{"learn":[66.42035707],"iteration":282,"passed_time":0.598311166,"remaining_time":1.515862565},
{"learn":[66.32248306],"iteration":283,"passed_time":0.6010775814,"remaining_time":1.515392776},
{"learn":[66.24977505],"iteration":284,"passed_time":0.6036961519,"remaining_time":1.51453596},
{"learn":[66.2129982],"iteration":285,"passed_time":0.6062274962,"remaining_time":1.513449064},
{"learn":[66.17374289],"iteration":286,"passed_time":0.608840608,"remaining_time":1.512555239},
{"learn":[66.11131573],"iteration":287,"passed_time":0.6121285947,"remaining_time":1.513317915},
{"learn":[66.08088718],"iteration":288,"passed_time":0.6146889453,"remaining_time":1.512262422},
{"learn":[65.9779383],"iteration":289,"passed_time":0.6172542109,"remaining_time":1.511208585},
{"learn":[65.92295912],"iteration":290,"passed_time":0.6198744568,"remaining_time":1.510278316},
{"learn":[65.86067142],"iteration":291,"passed_time":0.6220536807,"remaining_time":1.508267144},
{"learn":[65.81902149],"iteration":292,"passed_time":0.6244154303,"remaining_time":1.506695253},
{"learn":[65.77868725],"iteration":293,"passed_time":0.6267657711,"remaining_time":1.505090593},
{"learn":[65.7235526],"iteration":294,"passed_time":0.6285760654,"remaining_time":1.502190258},
{"learn":[65.68910144],"iteration":295,"passed_time":0.6311609592,"remaining_time":1.501139579},
{"learn":[65.63349876],"iteration":296,"passed_time":0.6332318749,"remaining_time":1.49886198},
{"learn":[65.58328381],"iteration":297,"passed_time":0.6350602718,"remaining_time":1.496014466},
{"learn":[65.5500227],"iteration":298,"passed_time":0.636833666,"remaining_time":1.493044816},
{"learn":[65.49299601],"iteration":299,"passed_time":0.6387235638,"remaining_time":1.490354982},
{"learn":[65.45388183],"iteration":300,"passed_time":0.6429824969,"remaining_time":1.493171978},
{"learn":[65.39077257],"iteration":301,"passed_time":0.6507204071,"remaining_time":1.503982928},
{"learn":[65.27750465],"iteration":302,"passed_time":0.6524091437,"remaining_time":1.500756347},
{"learn":[65.25146206],"iteration":303,"passed_time":0.6539579707,"remaining_time":1.497219565},
{"learn":[65.15053253],"iteration":304,"passed_time":0.6566311055,"remaining_time":1.496257765},
{"learn":[65.10746967],"iteration":305,"passed_time":0.6582567698,"remaining_time":1.492909145},
{"learn":[65.04646827],"iteration":306,"passed_time":0.6598770408,"remaining_time":1.489559574},
{"learn":[65.00513293],"iteration":307,"passed_time":0.6615527075,"remaining_time":1.486345694},
{"learn":[64.97460995],"iteration":308,"passed_time":0.6632426386,"remaining_time":1.483173668},
{"learn":[64.90288237],"iteration":309,"passed_time":0.6651392334,"remaining_time":1.480471197},
{"learn":[64.85004719],"iteration":310,"passed_time":0.6668052593,"remaining_time":1.477263099},
{"learn":[64.81471251],"iteration":311,"passed_time":0.6683847241,"remaining_time":1.473874007},
{"learn":[64.68846868],"iteration":312,"passed_time":0.6700398659,"remaining_time":1.470662581},
{"learn":[64.67644603],"iteration":313,"passed_time":0.6742041444,"remaining_time":1.472942812},
{"learn":[64.54840029],"iteration":314,"passed_time":0.6784272735,"remaining_time":1.475310103},
{"learn":[64.45888153],"iteration":315,"passed_time":0.680746712,"remaining_time":1.473515035},
{"learn":[64.40085905],"iteration":316,"passed_time":0.6825238444,"remaining_time":1.47054822},
{"learn":[64.3579356],"iteration":317,"passed_time":0.6843002015,"remaining_time":1.467587225},
{"learn":[64.32269767],"iteration":318,"passed_time":0.6860689741,"remaining_time":1.464617465},
{"learn":[64.28875696],"iteration":319,"passed_time":0.6887220297,"remaining_time":1.463534313},
{"learn":[64.23125541],"iteration":320,"passed_time":0.6906351853,"remaining_time":1.460876295},
{"learn":[64.19356103],"iteration":321,"passed_time":0.6924092847,"remaining_time":1.457930109},
{"learn":[64.16687548],"iteration":322,"passed_time":0.6942904491,"remaining_time":1.455215585},
{"learn":[64.09345675],"iteration":323,"passed_time":0.6961014302,"remaining_time":1.452359774},
{"learn":[64.02847656],"iteration":324,"passed_time":0.698244409,"remaining_time":1.450199926},
{"learn":[63.93369245],"iteration":325,"passed_time":0.700113514,"remaining_time":1.447473952},
{"learn":[63.82947005],"iteration":326,"passed_time":0.7020973559,"remaining_time":1.444989359},
{"learn":[63.77109809],"iteration":327,"passed_time":0.7045691637,"remaining_time":1.443507555},
{"learn":[63.71024092],"iteration":328,"passed_time":0.7071187251,"remaining_time":1.442178312},
{"learn":[63.67344128],"iteration":329,"passed_time":0.7103894221,"remaining_time":1.442305796},
{"learn":[63.6257136],"iteration":330,"passed_time":0.7130913306,"remaining_time":1.441263143},
{"learn":[63.54575783],"iteration":331,"passed_time":0.7153124261,"remaining_time":1.439243074},
{"learn":[63.48343614],"iteration":332,"passed_time":0.7178477556,"remaining_time":1.43785121},
{"learn":[63.4435713],"iteration":333,"passed_time":0.7199293291,"remaining_time":1.435547704},
{"learn":[63.35039677],"iteration":334,"passed_time":0.7219270742,"remaining_time":1.433079117},
{"learn":[63.30516789],"iteration":335,"passed_time":0.7246268969,"remaining_time":1.432000772},
{"learn":[63.22632796],"iteration":336,"passed_time":0.7264715612,"remaining_time":1.429230401},
{"learn":[63.18007392],"iteration":337,"passed_time":0.7283635994,"remaining_time":1.426558292},
{"learn":[63.06844757],"iteration":338,"passed_time":0.7303568028,"remaining_time":1.424088043},
{"learn":[62.97196398],"iteration":339,"passed_time":0.7324488538,"remaining_time":1.421812481},
{"learn":[62.94111329],"iteration":340,"passed_time":0.7353357354,"remaining_time":1.421074046},
{"learn":[62.88994833],"iteration":341,"passed_time":0.7376179793,"remaining_time":1.419159738},
{"learn":[62.80821086],"iteration":342,"passed_time":0.7395341743,"remaining_time":1.416542136},
{"learn":[62.76393273],"iteration":343,"passed_time":0.742833265,"remaining_time":1.416565761},
{"learn":[62.71801539],"iteration":344,"passed_time":0.7447551946,"remaining_time":1.413955514},
{"learn":[62.63468203],"iteration":345,"passed_time":0.7465903997,"remaining_time":1.411185322},
{"learn":[62.60744889],"iteration":346,"passed_time":0.7484636986,"remaining_time":1.408492205},
{"learn":[62.54729426],"iteration":347,"passed_time":0.750447093,"remaining_time":1.406010071},
{"learn":[62.48925372],"iteration":348,"passed_time":0.7531235183,"remaining_time":1.404823526},
{"learn":[62.42875478],"iteration":349,"passed_time":0.754960625,"remaining_time":1.402069732},
{"learn":[62.40605965],"iteration":350,"passed_time":0.7566983173,"remaining_time":1.399137345},
{"learn":[62.32990175],"iteration":351,"passed_time":0.7586270754,"remaining_time":1.39656348},
{"learn":[62.26212012],"iteration":352,"passed_time":0.7605297511,"remaining_time":1.393945465},
{"learn":[62.22661485],"iteration":353,"passed_time":0.7622881455,"remaining_time":1.391068198},
{"learn":[62.21755429],"iteration":354,"passed_time":0.7643300963,"remaining_time":1.388712428},
{"learn":[62.19104663],"iteration":355,"passed_time":0.7668811038,"remaining_time":1.3872793},
{"learn":[62.17078759],"iteration":356,"passed_time":0.7698246831,"remaining_time":1.386546978},
{"learn":[62.15275559],"iteration":357,"passed_time":0.7719569827,"remaining_time":1.384347438},
{"learn":[62.10076532],"iteration":358,"passed_time":0.7735913789,"remaining_time":1.381259259},
{"learn":[61.9783279],"iteration":359,"passed_time":0.7751203092,"remaining_time":1.377991661},
{"learn":[61.9379394],"iteration":360,"passed_time":0.776778367,"remaining_time":1.374962262},
{"learn":[61.85263353],"iteration":361,"passed_time":0.7783161019,"remaining_time":1.371728378},
{"learn":[61.79464986],"iteration":362,"passed_time":0.7800792327,"remaining_time":1.36889937},
{"learn":[61.73631728],"iteration":363,"passed_time":0.7833823089,"remaining_time":1.368766891},
{"learn":[61.66838237],"iteration":364,"passed_time":0.7850249791,"remaining_time":1.365728388},
{"learn":[61.59164147],"iteration":365,"passed_time":0.7866167697,"remaining_time":1.362609377},
{"learn":[61.52511841],"iteration":366,"passed_time":0.7882492909,"remaining_time":1.359568941},
{"learn":[61.48809041],"iteration":367,"passed_time":0.7900095327,"remaining_time":1.356755502},
{"learn":[61.43105854],"iteration":368,"passed_time":0.7921965788,"remaining_time":1.354677619},
{"learn":[61.35193397],"iteration":369,"passed_time":0.7941081672,"remaining_time":1.352130123},
{"learn":[61.32769622],"iteration":370,"passed_time":0.7965345696,"remaining_time":1.350458879},
{"learn":[61.26091206],"iteration":371,"passed_time":0.7990065283,"remaining_time":1.348860483},
{"learn":[61.22981313],"iteration":372,"passed_time":0.800617119,"remaining_time":1.345809474},
{"learn":[61.19436332],"iteration":373,"passed_time":0.8034882927,"remaining_time":1.344876126},
{"learn":[61.16756667],"iteration":374,"passed_time":0.8053848517,"remaining_time":1.342308086},
{"learn":[61.13655224],"iteration":375,"passed_time":0.8072803133,"remaining_time":1.339741797},
{"learn":[61.09325392],"iteration":376,"passed_time":0.8099165981,"remaining_time":1.338403291},
{"learn":[61.04653287],"iteration":377,"passed_time":0.8117432027,"remaining_time":1.335725587},
{"learn":[60.97902722],"iteration":378,"passed_time":0.8143371118,"remaining_time":1.334309621},
{"learn":[60.92622765],"iteration":379,"passed_time":0.8162813074,"remaining_time":1.331827396},
{"learn":[60.89822405],"iteration":380,"passed_time":0.8181457892,"remaining_time":1.329218487},
{"learn":[60.85607254],"iteration":381,"passed_time":0.8200704902,"remaining_time":1.326710898},
{"learn":[60.8125643],"iteration":382,"passed_time":0.8220229454,"remaining_time":1.324251063},
{"learn":[60.74994104],"iteration":383,"passed_time":0.8238300491,"remaining_time":1.321560704},
{"learn":[60.65357054],"iteration":384,"passed_time":0.8264509739,"remaining_time":1.320174932},
{"learn":[60.61183484],"iteration":385,"passed_time":0.8284502416,"remaining_time":1.317793908},
{"learn":[60.55306206],"iteration":386,"passed_time":0.8303042869,"remaining_time":1.315184827},
{"learn":[60.47681457],"iteration":387,"passed_time":0.8321101499,"remaining_time":1.312503639},
{"learn":[60.40529218],"iteration":388,"passed_time":0.8339816513,"remaining_time":1.309930049},
{"learn":[60.32112972],"iteration":389,"passed_time":0.8366818571,"remaining_time":1.308656238},
{"learn":[60.31971701],"iteration":390,"passed_time":0.839241897,"remaining_time":1.307156817},
{"learn":[60.29692281],"iteration":391,"passed_time":0.841057299,"remaining_time":1.304497035},
{"learn":[60.2181615],"iteration":392,"passed_time":0.8429745726,"remaining_time":1.301998895},
{"learn":[60.13052665],"iteration":393,"passed_time":0.8447707453,"remaining_time":1.299317441},
{"learn":[60.1269745],"iteration":394,"passed_time":0.8466757182,"remaining_time":1.296807113},
{"learn":[60.04893813],"iteration":395,"passed_time":0.848826495,"remaining_time":1.294674755},
{"learn":[59.99012114],"iteration":396,"passed_time":0.850644172,"remaining_time":1.292036362},
{"learn":[59.90640419],"iteration":397,"passed_time":0.8526301418,"remaining_time":1.289656647},
{"learn":[59.87372128],"iteration":398,"passed_time":0.8544492466,"remaining_time":1.287027562},
{"learn":[59.83884237],"iteration":399,"passed_time":0.8564760632,"remaining_time":1.284714095},
{"learn":[59.7874439],"iteration":400,"passed_time":0.8583645243,"remaining_time":1.282195387},
{"learn":[59.74467203],"iteration":401,"passed_time":0.8602197513,"remaining_time":1.279630376},
{"learn":[59.67160687],"iteration":402,"passed_time":0.8621237514,"remaining_time":1.27714114},
{"learn":[59.6323965],"iteration":403,"passed_time":0.8639139219,"remaining_time":1.274486875},
{"learn":[59.5602664],"iteration":404,"passed_time":0.8658124856,"remaining_time":1.271996121},
{"learn":[59.5143952],"iteration":405,"passed_time":0.8690691537,"remaining_time":1.271495264},
{"learn":[59.47318313],"iteration":406,"passed_time":0.8709674988,"remaining_time":1.269001786},
{"learn":[59.42382871],"iteration":407,"passed_time":0.8727336918,"remaining_time":1.266319474},
{"learn":[59.38075374],"iteration":408,"passed_time":0.874492084,"remaining_time":1.263630371},
{"learn":[59.3204326],"iteration":409,"passed_time":0.8763439063,"remaining_time":1.261080255},
{"learn":[59.29047414],"iteration":410,"passed_time":0.8794753176,"remaining_time":1.260367304},
{"learn":[59.23708196],"iteration":411,"passed_time":0.8812708685,"remaining_time":1.257736094},
{"learn":[59.2157876],"iteration":412,"passed_time":0.8830997665,"remaining_time":1.255156327},
{"learn":[59.14487308],"iteration":413,"passed_time":0.8850220349,"remaining_time":1.252712349},
{"learn":[59.1297475],"iteration":414,"passed_time":0.8873107896,"remaining_time":1.250787499},
{"learn":[59.11635139],"iteration":415,"passed_time":0.8918487766,"remaining_time":1.252018475},
{"learn":[59.06759693],"iteration":416,"passed_time":0.8970291121,"remaining_time":1.254119838},
{"learn":[58.99290838],"iteration":417,"passed_time":0.8986238343,"remaining_time":1.251193951},
{"learn":[58.92978762],"iteration":418,"passed_time":0.900234711,"remaining_time":1.248296819},
{"learn":[58.89053995],"iteration":419,"passed_time":0.902580132,"remaining_time":1.246420182},
{"learn":[58.84086641],"iteration":420,"passed_time":0.904214753,"remaining_time":1.243563758},
{"learn":[58.78972374],"iteration":421,"passed_time":0.9057629228,"remaining_time":1.240594714},
{"learn":[58.72377555],"iteration":422,"passed_time":0.907385505,"remaining_time":1.237733892},
{"learn":[58.65780971],"iteration":423,"passed_time":0.9097854272,"remaining_time":1.23593492},
{"learn":[58.5945741],"iteration":424,"passed_time":0.9141403615,"remaining_time":1.236778136},
{"learn":[58.56202667],"iteration":425,"passed_time":0.9180797208,"remaining_time":1.237036995},
{"learn":[58.52216228],"iteration":426,"passed_time":0.9215225983,"remaining_time":1.23660995},
{"learn":[58.49357126],"iteration":427,"passed_time":0.9248675033,"remaining_time":1.236037878},
{"learn":[58.45981417],"iteration":428,"passed_time":0.9273852088,"remaining_time":1.234351875},
{"learn":[58.44378028],"iteration":429,"passed_time":0.9295240556,"remaining_time":1.232159795},
{"learn":[58.39026215],"iteration":430,"passed_time":0.9318639438,"remaining_time":1.230233374},
{"learn":[58.33329802],"iteration":431,"passed_time":0.9348816276,"remaining_time":1.229196214},
{"learn":[58.30511078],"iteration":432,"passed_time":0.9373367078,"remaining_time":1.227413195},
{"learn":[58.28320587],"iteration":433,"passed_time":0.9400060478,"remaining_time":1.225906505},
{"learn":[58.2334088],"iteration":434,"passed_time":0.9424686768,"remaining_time":1.224125983},
{"learn":[58.22442275],"iteration":435,"passed_time":0.9457227208,"remaining_time":1.223366088},
{"learn":[58.15321765],"iteration":436,"passed_time":0.9481529223,"remaining_time":1.221533399},
{"learn":[58.1106003],"iteration":437,"passed_time":0.9516898127,"remaining_time":1.221117979},
{"learn":[58.05281913],"iteration":438,"passed_time":0.9542319976,"remaining_time":1.2194172},
{"learn":[58.00415273],"iteration":439,"passed_time":0.9567015369,"remaining_time":1.217620138},
{"learn":[57.95125811],"iteration":440,"passed_time":0.9588697996,"remaining_time":1.215438136},
{"learn":[57.92513331],"iteration":441,"passed_time":0.9615225951,"remaining_time":1.213867892},
{"learn":[57.90224903],"iteration":442,"passed_time":0.9640327776,"remaining_time":1.212113447},
{"learn":[57.85374374],"iteration":443,"passed_time":0.9664535767,"remaining_time":1.210243668},
{"learn":[57.83786404],"iteration":444,"passed_time":0.9689150573,"remaining_time":1.20842215},
{"learn":[57.79728265],"iteration":445,"passed_time":0.9713674886,"remaining_time":1.206586522},
{"learn":[57.73547783],"iteration":446,"passed_time":0.9752240823,"remaining_time":1.206485274},
{"learn":[57.67230452],"iteration":447,"passed_time":0.9779816544,"remaining_time":1.20501311},
{"learn":[57.62669619],"iteration":448,"passed_time":0.9805329317,"remaining_time":1.203282061},
{"learn":[57.57359295],"iteration":449,"passed_time":0.982806464,"remaining_time":1.2012079},
{"learn":[57.52045698],"iteration":450,"passed_time":0.9860850357,"remaining_time":1.200356285},
{"learn":[57.48014513],"iteration":451,"passed_time":0.9890314495,"remaining_time":1.199091226},
{"learn":[57.45999614],"iteration":452,"passed_time":0.991556396,"remaining_time":1.19730982},
{"learn":[57.44604467],"iteration":453,"passed_time":0.9940513993,"remaining_time":1.195489128},
{"learn":[57.3829264],"iteration":454,"passed_time":0.9963852177,"remaining_time":1.193472404},
{"learn":[57.3494752],"iteration":455,"passed_time":0.9988939832,"remaining_time":1.191662997},
{"learn":[57.31678142],"iteration":456,"passed_time":1.001189562,"remaining_time":1.189597225},
{"learn":[57.25397767],"iteration":457,"passed_time":1.00355423,"remaining_time":1.187612211},
{"learn":[57.21922263],"iteration":458,"passed_time":1.005954046,"remaining_time":1.185666969},
{"learn":[57.19126211],"iteration":459,"passed_time":1.009381478,"remaining_time":1.184926083},
{"learn":[57.16853528],"iteration":460,"passed_time":1.011835796,"remaining_time":1.183035779},
{"learn":[57.10542278],"iteration":461,"passed_time":1.014591209,"remaining_time":1.181493659},
{"learn":[56.9915075],"iteration":462,"passed_time":1.016497428,"remaining_time":1.17896138},
{"learn":[56.91816489],"iteration":463,"passed_time":1.018450543,"remaining_time":1.176485973},
{"learn":[56.9125186],"iteration":464,"passed_time":1.020384008,"remaining_time":1.173990202},
{"learn":[56.85857894],"iteration":465,"passed_time":1.022258338,"remaining_time":1.171429082},
{"learn":[56.78479145],"iteration":466,"passed_time":1.024637712,"remaining_time":1.169447324},
{"learn":[56.69789178],"iteration":467,"passed_time":1.027399193,"remaining_time":1.167898228},
{"learn":[56.69307215],"iteration":468,"passed_time":1.029262544,"remaining_time":1.165327103},
{"learn":[56.6725576],"iteration":469,"passed_time":1.032700232,"remaining_time":1.164534304},
{"learn":[56.63935285],"iteration":470,"passed_time":1.035130381,"remaining_time":1.162598665},
{"learn":[56.56765146],"iteration":471,"passed_time":1.038293143,"remaining_time":1.161480465},
{"learn":[56.54655557],"iteration":472,"passed_time":1.040936974,"remaining_time":1.159775444},
{"learn":[56.53337426],"iteration":473,"passed_time":1.043344573,"remaining_time":1.157804315},
{"learn":[56.48755949],"iteration":474,"passed_time":1.046771071,"remaining_time":1.156957499},
{"learn":[56.42986496],"iteration":475,"passed_time":1.050060067,"remaining_time":1.155948477},
{"learn":[56.40695544],"iteration":476,"passed_time":1.052346232,"remaining_time":1.153830355},
{"learn":[56.35400132],"iteration":477,"passed_time":1.054868709,"remaining_time":1.151969594},
{"learn":[56.34495579],"iteration":478,"passed_time":1.058853211,"remaining_time":1.15169629},
{"learn":[56.29023248],"iteration":479,"passed_time":1.061365424,"remaining_time":1.149812542},
{"learn":[56.28271052],"iteration":480,"passed_time":1.063700004,"remaining_time":1.147734516},
{"learn":[56.25341166],"iteration":481,"passed_time":1.066116774,"remaining_time":1.145743753},
{"learn":[56.19107389],"iteration":482,"passed_time":1.068245913,"remaining_time":1.143443348},
{"learn":[56.14577948],"iteration":483,"passed_time":1.070065957,"remaining_time":1.140814119},
{"learn":[56.14265504],"iteration":484,"passed_time":1.071893608,"remaining_time":1.138196305},
{"learn":[56.13196009],"iteration":485,"passed_time":1.073833736,"remaining_time":1.1357007},
{"learn":[56.11187918],"iteration":486,"passed_time":1.076184452,"remaining_time":1.133639884},
{"learn":[56.07606261],"iteration":487,"passed_time":1.07807275,"remaining_time":1.131092721},
{"learn":[56.01208928],"iteration":488,"passed_time":1.08108922,"remaining_time":1.129727181},
{"learn":[55.97999628],"iteration":489,"passed_time":1.082973941,"remaining_time":1.127176959},
{"learn":[55.91221382],"iteration":490,"passed_time":1.084776846,"remaining_time":1.124544633},
{"learn":[55.89163124],"iteration":491,"passed_time":1.087460992,"remaining_time":1.122825577},
{"learn":[55.89035894],"iteration":492,"passed_time":1.089168283,"remaining_time":1.120098011},
{"learn":[55.83988662],"iteration":493,"passed_time":1.091817994,"remaining_time":1.118339889},
{"learn":[55.80588816],"iteration":494,"passed_time":1.093616789,"remaining_time":1.115710058},
{"learn":[55.7641548],"iteration":495,"passed_time":1.095519787,"remaining_time":1.113189461},
{"learn":[55.74117563],"iteration":496,"passed_time":1.097340134,"remaining_time":1.110587701},
{"learn":[55.72335002],"iteration":497,"passed_time":1.099221445,"remaining_time":1.108050533},
{"learn":[55.66897831],"iteration":498,"passed_time":1.101414818,"remaining_time":1.105829306},
{"learn":[55.66465991],"iteration":499,"passed_time":1.103316654,"remaining_time":1.103316654},
{"learn":[55.63381925],"iteration":500,"passed_time":1.10535912,"remaining_time":1.100946509},
{"learn":[55.59734164],"iteration":501,"passed_time":1.107105517,"remaining_time":1.098283959},
{"learn":[55.53438057],"iteration":502,"passed_time":1.109035029,"remaining_time":1.095805983},
{"learn":[55.4997101],"iteration":503,"passed_time":1.110801512,"remaining_time":1.093169742},
{"learn":[55.46435162],"iteration":504,"passed_time":1.113184032,"remaining_time":1.091140784},
{"learn":[55.43057157],"iteration":505,"passed_time":1.115875095,"remaining_time":1.089411654},
{"learn":[55.38864576],"iteration":506,"passed_time":1.118221882,"remaining_time":1.08734396},
{"learn":[55.33409149],"iteration":507,"passed_time":1.120087677,"remaining_time":1.084809325},
{"learn":[55.29018225],"iteration":508,"passed_time":1.121830098,"remaining_time":1.082158307},
{"learn":[55.24041085],"iteration":509,"passed_time":1.124803085,"remaining_time":1.08069316},
{"learn":[55.18512971],"iteration":510,"passed_time":1.126973097,"remaining_time":1.078453708},
{"learn":[55.16858502],"iteration":511,"passed_time":1.128855254,"remaining_time":1.075940164},
{"learn":[55.13796769],"iteration":512,"passed_time":1.130786584,"remaining_time":1.073475763},
{"learn":[55.11930283],"iteration":513,"passed_time":1.133178028,"remaining_time":1.071448485},
{"learn":[55.07134528],"iteration":514,"passed_time":1.136274272,"remaining_time":1.070083538},
{"learn":[55.0228513],"iteration":515,"passed_time":1.13793182,"remaining_time":1.067362405},
{"learn":[55.00076223],"iteration":516,"passed_time":1.139574411,"remaining_time":1.064631413},
{"learn":[54.96681013],"iteration":517,"passed_time":1.141330383,"remaining_time":1.062010124},
{"learn":[54.94665953],"iteration":518,"passed_time":1.143438729,"remaining_time":1.059718745},
{"learn":[54.89875122],"iteration":519,"passed_time":1.145061494,"remaining_time":1.056979841},
{"learn":[54.82263108],"iteration":520,"passed_time":1.146658657,"remaining_time":1.054221683},
{"learn":[54.81860432],"iteration":521,"passed_time":1.148890845,"remaining_time":1.052049471},
{"learn":[54.79593138],"iteration":522,"passed_time":1.150730684,"remaining_time":1.04951919},
{"learn":[54.75823455],"iteration":523,"passed_time":1.154112861,"remaining_time":1.048392599},
{"learn":[54.73635974],"iteration":524,"passed_time":1.156053037,"remaining_time":1.045952747},
{"learn":[54.71102067],"iteration":525,"passed_time":1.157835837,"remaining_time":1.043372979},
{"learn":[54.69725344],"iteration":526,"passed_time":1.159580167,"remaining_time":1.040761706},
{"learn":[54.60897634],"iteration":527,"passed_time":1.161467042,"remaining_time":1.038281144},
{"learn":[54.57220069],"iteration":528,"passed_time":1.164993608,"remaining_time":1.03726274},
{"learn":[54.51902124],"iteration":529,"passed_time":1.16690164,"remaining_time":1.034799568},
{"learn":[54.46246854],"iteration":530,"passed_time":1.168791762,"remaining_time":1.032322667},
{"learn":[54.44228468],"iteration":531,"passed_time":1.170578671,"remaining_time":1.029757177},
{"learn":[54.39898298],"iteration":532,"passed_time":1.172500878,"remaining_time":1.027313152},
{"learn":[54.32474797],"iteration":533,"passed_time":1.175431241,"remaining_time":1.025750858},
{"learn":[54.29925077],"iteration":534,"passed_time":1.177299434,"remaining_time":1.023260255},
{"learn":[54.27541266],"iteration":535,"passed_time":1.179017549,"remaining_time":1.020642057},
{"learn":[54.25131423],"iteration":536,"passed_time":1.180843631,"remaining_time":1.0181203},
{"learn":[54.23290719],"iteration":537,"passed_time":1.182740956,"remaining_time":1.015662308},
{"learn":[54.21969362],"iteration":538,"passed_time":1.184814083,"remaining_time":1.013356757},
{"learn":[54.17016307],"iteration":539,"passed_time":1.187037465,"remaining_time":1.011180063},
{"learn":[54.12674688],"iteration":540,"passed_time":1.188925946,"remaining_time":1.008719056},
{"learn":[54.11788297],"iteration":541,"passed_time":1.191348759,"remaining_time":1.006711682},
{"learn":[54.0967127],"iteration":542,"passed_time":1.193536339,"remaining_time":1.004504801},
{"learn":[54.04133464],"iteration":543,"passed_time":1.195420704,"remaining_time":1.002043826},
{"learn":[53.99338472],"iteration":544,"passed_time":1.197343968,"remaining_time":0.9996174409},
{"learn":[53.95041438],"iteration":545,"passed_time":1.199232628,"remaining_time":0.9971641264},
{"learn":[53.91954756],"iteration":546,"passed_time":1.201074606,"remaining_time":0.9946742163},
{"learn":[53.88849733],"iteration":547,"passed_time":1.203334438,"remaining_time":0.9925313249},
{"learn":[53.87786235],"iteration":548,"passed_time":1.205526294,"remaining_time":0.9903321652},
{"learn":[53.85866698],"iteration":549,"passed_time":1.208125418,"remaining_time":0.9884662508},
{"learn":[53.81676755],"iteration":550,"passed_time":1.210530167,"remaining_time":0.9864392834},
{"learn":[53.77224578],"iteration":551,"passed_time":1.213253399,"remaining_time":0.9846694253},
{"learn":[53.73345793],"iteration":552,"passed_time":1.215179256,"remaining_time":0.9822515868},
{"learn":[53.71339038],"iteration":553,"passed_time":1.218033724,"remaining_time":0.9805831066},
{"learn":[53.66953223],"iteration":554,"passed_time":1.220076364,"remaining_time":0.9782594268},
{"learn":[53.62192054],"iteration":555,"passed_time":1.221954081,"remaining_time":0.9758050572},
{"learn":[53.58647763],"iteration":556,"passed_time":1.223901027,"remaining_time":0.9734078189},
{"learn":[53.56008808],"iteration":557,"passed_time":1.225796247,"remaining_time":0.9709712206},
{"learn":[53.52392966],"iteration":558,"passed_time":1.229051019,"remaining_time":0.9696091226},
{"learn":[53.50744318],"iteration":559,"passed_time":1.230981737,"remaining_time":0.9671999359},
{"learn":[53.41831636],"iteration":560,"passed_time":1.233176318,"remaining_time":0.9649989365},
{"learn":[53.41243381],"iteration":561,"passed_time":1.235020933,"remaining_time":0.9625252112},
{"learn":[53.38021972],"iteration":562,"passed_time":1.236992732,"remaining_time":0.9601524405},
{"learn":[53.36945142],"iteration":563,"passed_time":1.239601074,"remaining_time":0.9582731707},
{"learn":[53.29873113],"iteration":564,"passed_time":1.241524271,"remaining_time":0.9558638192},
{"learn":[53.22239694],"iteration":565,"passed_time":1.243425183,"remaining_time":0.9534390982},
{"learn":[53.18204145],"iteration":566,"passed_time":1.245218241,"remaining_time":0.9509338594},
{"learn":[53.12335784],"iteration":567,"passed_time":1.247063239,"remaining_time":0.9484706328},
{"learn":[53.09222424],"iteration":568,"passed_time":1.248884502,"remaining_time":0.9459915996},
{"learn":[53.06963611],"iteration":569,"passed_time":1.252357343,"remaining_time":0.9447608029},
{"learn":[53.02586104],"iteration":570,"passed_time":1.257631464,"remaining_time":0.9448754779},
{"learn":[53.01550643],"iteration":571,"passed_time":1.259587281,"remaining_time":0.9424883848},
{"learn":[52.97648032],"iteration":572,"passed_time":1.261941859,"remaining_time":0.9403999543},
{"learn":[52.94424422],"iteration":573,"passed_time":1.263530959,"remaining_time":0.9377424885},
{"learn":[52.90767468],"iteration":574,"passed_time":1.265218258,"remaining_time":0.935161321},
{"learn":[52.86221448],"iteration":575,"passed_time":1.266830296,"remaining_time":0.9325278567},
{"learn":[52.84031049],"iteration":576,"passed_time":1.268431514,"remaining_time":0.929890001},
{"learn":[52.8338408],"iteration":577,"passed_time":1.269967809,"remaining_time":0.9272083311},
{"learn":[52.77211916],"iteration":578,"passed_time":1.27360109,"remaining_time":0.9260553693},
{"learn":[52.74695441],"iteration":579,"passed_time":1.275518887,"remaining_time":0.9236516079},
{"learn":[52.73608893],"iteration":580,"passed_time":1.277241586,"remaining_time":0.9211088201},
{"learn":[52.72421378],"iteration":581,"passed_time":1.279006711,"remaining_time":0.9185993214},
{"learn":[52.69237635],"iteration":582,"passed_time":1.280853432,"remaining_time":0.9161507392},
{"learn":[52.67821907],"iteration":583,"passed_time":1.28256308,"remaining_time":0.9136065773},
{"learn":[52.64891131],"iteration":584,"passed_time":1.284459291,"remaining_time":0.911197617},
{"learn":[52.61662199],"iteration":585,"passed_time":1.286275869,"remaining_time":0.9087341462},
{"learn":[52.58087822],"iteration":586,"passed_time":1.288099313,"remaining_time":0.9062777111},
{"learn":[52.52531639],"iteration":587,"passed_time":1.2899668,"remaining_time":0.9038542885},
{"learn":[52.47748577],"iteration":588,"passed_time":1.294744174,"remaining_time":0.9034632519},
{"learn":[52.43432732],"iteration":589,"passed_time":1.296570853,"remaining_time":0.901006864},
{"learn":[52.40767546],"iteration":590,"passed_time":1.29840942,"remaining_time":0.8985608338},
{"learn":[52.40427213],"iteration":591,"passed_time":1.300199978,"remaining_time":0.8960837688},
{"learn":[52.35640115],"iteration":592,"passed_time":1.302094907,"remaining_time":0.8936806526},
{"learn":[52.32928877],"iteration":593,"passed_time":1.304762418,"remaining_time":0.8918073091},
{"learn":[52.30322498],"iteration":594,"passed_time":1.306684665,"remaining_time":0.8894240155},
{"learn":[52.28474434],"iteration":595,"passed_time":1.308353158,"remaining_time":0.8868702617},
{"learn":[52.2811493],"iteration":596,"passed_time":1.310151722,"remaining_time":0.8844072763},
{"learn":[52.27529305],"iteration":597,"passed_time":1.311977336,"remaining_time":0.8819646975},
{"learn":[52.26414593],"iteration":598,"passed_time":1.314033861,"remaining_time":0.8796787616},
{"learn":[52.25626653],"iteration":599,"passed_time":1.315922988,"remaining_time":0.877281992},
{"learn":[52.23506959],"iteration":600,"passed_time":1.317812094,"remaining_time":0.8748868976},
{"learn":[52.20995584],"iteration":601,"passed_time":1.319558816,"remaining_time":0.8723993501},
{"learn":[52.15779223],"iteration":602,"passed_time":1.321339204,"remaining_time":0.8699364245},
{"learn":[52.11721485],"iteration":603,"passed_time":1.323282386,"remaining_time":0.8675824916},
{"learn":[52.0663674],"iteration":604,"passed_time":1.32556688,"remaining_time":0.8654527567},
{"learn":[52.00894015],"iteration":605,"passed_time":1.327436769,"remaining_time":0.8630529487},
{"learn":[51.95656213],"iteration":606,"passed_time":1.329194086,"remaining_time":0.8605820028},
{"learn":[51.92094796],"iteration":607,"passed_time":1.331200551,"remaining_time":0.8582740391},
{"learn":[51.88974691],"iteration":608,"passed_time":1.333691127,"remaining_time":0.8562778831},
{"learn":[51.83881785],"iteration":609,"passed_time":1.337285176,"remaining_time":0.854985604},
{"learn":[51.79419589],"iteration":610,"passed_time":1.339177109,"remaining_time":0.85260212},
{"learn":[51.78229023],"iteration":611,"passed_time":1.341034726,"remaining_time":0.8501984864},
{"learn":[51.77786186],"iteration":612,"passed_time":1.342891998,"remaining_time":0.8477964167},
{"learn":[51.75607868],"iteration":613,"passed_time":1.344840921,"remaining_time":0.8454537383},
{"learn":[51.71652058],"iteration":614,"passed_time":1.347575866,"remaining_time":0.8436044038},
{"learn":[51.68059408],"iteration":615,"passed_time":1.349426851,"remaining_time":0.841201154},
{"learn":[51.6442201],"iteration":616,"passed_time":1.351357372,"remaining_time":0.8388490655},
{"learn":[51.61695414],"iteration":617,"passed_time":1.353270799,"remaining_time":0.8364877757},
{"learn":[51.59409452],"iteration":618,"passed_time":1.355037083,"remaining_time":0.8340373646},
{"learn":[51.56862288],"iteration":619,"passed_time":1.357165252,"remaining_time":0.8318109611},
{"learn":[51.5192839],"iteration":620,"passed_time":1.359029433,"remaining_time":0.8294237604},
{"learn":[51.50230565],"iteration":621,"passed_time":1.361623046,"remaining_time":0.8274815294},
{"learn":[51.48516091],"iteration":622,"passed_time":1.363510178,"remaining_time":0.8251096906},
{"learn":[51.47723284],"iteration":623,"passed_time":1.365331333,"remaining_time":0.8226996494},
{"learn":[51.47331623],"iteration":624,"passed_time":1.367020729,"remaining_time":0.8202124374},
{"learn":[51.42275672],"iteration":625,"passed_time":1.368958773,"remaining_time":0.8178763279},
{"learn":[51.37800731],"iteration":626,"passed_time":1.372528527,"remaining_time":0.8165121857},
{"learn":[51.33607174],"iteration":627,"passed_time":1.374816919,"remaining_time":0.8143819968},
{"learn":[51.33542509],"iteration":628,"passed_time":1.37785186,"remaining_time":0.8126916378},
{"learn":[51.31036056],"iteration":629,"passed_time":1.38310334,"remaining_time":0.8122987871},
{"learn":[51.2930801],"iteration":630,"passed_time":1.384656219,"remaining_time":0.8097276462},
{"learn":[51.26841971],"iteration":631,"passed_time":1.386245989,"remaining_time":0.8071812086},
{"learn":[51.24366675],"iteration":632,"passed_time":1.387824645,"remaining_time":0.8046313502},
{"learn":[51.22221361],"iteration":633,"passed_time":1.390802201,"remaining_time":0.8028921222},
{"learn":[51.19689257],"iteration":634,"passed_time":1.393034418,"remaining_time":0.8007205708},
{"learn":[51.17788268],"iteration":635,"passed_time":1.394908831,"remaining_time":0.798344048},
{"learn":[51.149659],"iteration":636,"passed_time":1.396625755,"remaining_time":0.7958793546},
{"learn":[51.12655018],"iteration":637,"passed_time":1.398428122,"remaining_time":0.7934654862},
{"learn":[51.10744202],"iteration":638,"passed_time":1.401788638,"remaining_time":0.7919338004},
{"learn":[51.06712878],"iteration":639,"passed_time":1.403810812,"remaining_time":0.7896435819},
{"learn":[51.01565589],"iteration":640,"passed_time":1.405674665,"remaining_time":0.7872655302},
{"learn":[51.00858003],"iteration":641,"passed_time":1.407415786,"remaining_time":0.7848206405},
{"learn":[50.99601313],"iteration":642,"passed_time":1.409141627,"remaining_time":0.7823694568},
{"learn":[50.97768858],"iteration":643,"passed_time":1.411717239,"remaining_time":0.780390275},
{"learn":[50.93058495],"iteration":644,"passed_time":1.413645001,"remaining_time":0.7780526748},
{"learn":[50.78125726],"iteration":645,"passed_time":1.415573594,"remaining_time":0.7757167989},
{"learn":[50.75802904],"iteration":646,"passed_time":1.417395336,"remaining_time":0.7733238851},
{"learn":[50.66202508],"iteration":647,"passed_time":1.419166278,"remaining_time":0.7709051385},
{"learn":[50.64392377],"iteration":648,"passed_time":1.421062217,"remaining_time":0.7685559907},
{"learn":[50.62727404],"iteration":649,"passed_time":1.423675977,"remaining_time":0.7665947567},
{"learn":[50.62414259],"iteration":650,"passed_time":1.425604676,"remaining_time":0.764264258},
{"learn":[50.6139955],"iteration":651,"passed_time":1.427387627,"remaining_time":0.7618571999},
{"learn":[50.56253145],"iteration":652,"passed_time":1.42931168,"remaining_time":0.7595270338},
{"learn":[50.52292274],"iteration":653,"passed_time":1.431260511,"remaining_time":0.7572112184},
{"learn":[50.51455672],"iteration":654,"passed_time":1.433993917,"remaining_time":0.7553097733},
{"learn":[50.48007003],"iteration":655,"passed_time":1.435790896,"remaining_time":0.7529147384},
{"learn":[50.46906409],"iteration":656,"passed_time":1.437552063,"remaining_time":0.7505028274},
{"learn":[50.45416019],"iteration":657,"passed_time":1.439475078,"remaining_time":0.7481770162},
{"learn":[50.43011042],"iteration":658,"passed_time":1.441314422,"remaining_time":0.7458091316},
{"learn":[50.4052877],"iteration":659,"passed_time":1.443370527,"remaining_time":0.743554514},
{"learn":[50.38117919],"iteration":660,"passed_time":1.445366421,"remaining_time":0.7412696167},
{"learn":[50.36971135],"iteration":661,"passed_time":1.447102731,"remaining_time":0.7388530562},
{"learn":[50.3351319],"iteration":662,"passed_time":1.448991209,"remaining_time":0.7365158935},
{"learn":[50.32505891],"iteration":663,"passed_time":1.450838957,"remaining_time":0.7341594725},
{"learn":[50.28409535],"iteration":664,"passed_time":1.452779326,"remaining_time":0.7318512392},
{"learn":[50.27793489],"iteration":665,"passed_time":1.455258348,"remaining_time":0.7298142467},
{"learn":[50.22942515],"iteration":666,"passed_time":1.457037019,"remaining_time":0.7274262779},
{"learn":[50.19970337],"iteration":667,"passed_time":1.45912612,"remaining_time":0.7251944191},
{"learn":[50.16321027],"iteration":668,"passed_time":1.461303126,"remaining_time":0.7230064796},
{"learn":[50.15322756],"iteration":669,"passed_time":1.463172266,"remaining_time":0.720666937},
{"learn":[50.12972785],"iteration":670,"passed_time":1.465614749,"remaining_time":0.7186099141},
{"learn":[50.07001553],"iteration":671,"passed_time":1.467501853,"remaining_time":0.7162806666},
{"learn":[50.04859431],"iteration":672,"passed_time":1.469428709,"remaining_time":0.7139720474},
{"learn":[50.01060809],"iteration":673,"passed_time":1.471651131,"remaining_time":0.7118075203},
{"learn":[49.95858391],"iteration":674,"passed_time":1.473541203,"remaining_time":0.7094828012},
{"learn":[49.92513787],"iteration":675,"passed_time":1.475305301,"remaining_time":0.7070989904},
{"learn":[49.91699166],"iteration":676,"passed_time":1.477122939,"remaining_time":0.7047425541},
{"learn":[49.87472332],"iteration":677,"passed_time":1.479024109,"remaining_time":0.7024273794},
{"learn":[49.83995635],"iteration":678,"passed_time":1.480928936,"remaining_time":0.7001151526},
{"learn":[49.81632092],"iteration":679,"passed_time":1.482786757,"remaining_time":0.6977820033},
{"learn":[49.75279051],"iteration":680,"passed_time":1.484689607,"remaining_time":0.695471343},
{"learn":[49.70009699],"iteration":681,"passed_time":1.487728465,"remaining_time":0.6936915715},
{"learn":[49.69414543],"iteration":682,"passed_time":1.48962932,"remaining_time":0.6913799333},
{"learn":[49.60303975],"iteration":683,"passed_time":1.491537757,"remaining_time":0.6890729988},
{"learn":[49.58170599],"iteration":684,"passed_time":1.493432936,"remaining_time":0.6867611312},
{"learn":[49.55984439],"iteration":685,"passed_time":1.495187524,"remaining_time":0.6843861263},
{"learn":[49.55280137],"iteration":686,"passed_time":1.498255359,"remaining_time":0.6826112481},
{"learn":[49.52449929],"iteration":687,"passed_time":1.502236973,"remaining_time":0.6812469992},
{"learn":[49.47635531],"iteration":688,"passed_time":1.503910532,"remaining_time":0.6788333461},
{"learn":[49.42886642],"iteration":689,"passed_time":1.506507815,"remaining_time":0.6768368442},
{"learn":[49.41035132],"iteration":690,"passed_time":1.508281951,"remaining_time":0.6744705106},
{"learn":[49.37487313],"iteration":691,"passed_time":1.509878,"remaining_time":0.6720266243},
{"learn":[49.35078876],"iteration":692,"passed_time":1.512179374,"remaining_time":0.6698976449},
{"learn":[49.33251933],"iteration":693,"passed_time":1.514075465,"remaining_time":0.6675894702},
{"learn":[49.32501814],"iteration":694,"passed_time":1.51607406,"remaining_time":0.6653274654},
{"learn":[49.29266899],"iteration":695,"passed_time":1.518135984,"remaining_time":0.6630938779},
{"learn":[49.22918033],"iteration":696,"passed_time":1.51999185,"remaining_time":0.6607712059},
{"learn":[49.22085009],"iteration":697,"passed_time":1.521854894,"remaining_time":0.6584529772},
{"learn":[49.19927949],"iteration":698,"passed_time":1.523634879,"remaining_time":0.656100284},
{"learn":[49.09635308],"iteration":699,"passed_time":1.525409061,"remaining_time":0.6537467404},
{"learn":[49.06704853],"iteration":700,"passed_time":1.528798233,"remaining_time":0.6520836972},
{"learn":[49.03401728],"iteration":701,"passed_time":1.530591746,"remaining_time":0.6497383764},
{"learn":[49.01515005],"iteration":702,"passed_time":1.532447472,"remaining_time":0.647420909},
{"learn":[48.99462177],"iteration":703,"passed_time":1.534333719,"remaining_time":0.6451175864},
{"learn":[48.96877658],"iteration":704,"passed_time":1.536127717,"remaining_time":0.642776846},
{"learn":[48.95141029],"iteration":705,"passed_time":1.539134047,"remaining_time":0.6409425068},
{"learn":[48.91583068],"iteration":706,"passed_time":1.541728181,"remaining_time":0.638934027},
{"learn":[48.90552491],"iteration":707,"passed_time":1.543518502,"remaining_time":0.6365923763},
{"learn":[48.88579026],"iteration":708,"passed_time":1.545389559,"remaining_time":0.6342854186},
{"learn":[48.8674462],"iteration":709,"passed_time":1.54710031,"remaining_time":0.6319142111},
{"learn":[48.83771045],"iteration":710,"passed_time":1.549245173,"remaining_time":0.629721315},
{"learn":[48.80775063],"iteration":711,"passed_time":1.55112424,"remaining_time":0.627421041},
{"learn":[48.77423964],"iteration":712,"passed_time":1.552973349,"remaining_time":0.6251098896},
{"learn":[48.73188615],"iteration":713,"passed_time":1.554821351,"remaining_time":0.6227995887},
{"learn":[48.71319227],"iteration":714,"passed_time":1.556681081,"remaining_time":0.6204952562},
{"learn":[48.70569143],"iteration":715,"passed_time":1.558806571,"remaining_time":0.6182975786},
{"learn":[48.69935545],"iteration":716,"passed_time":1.560996653,"remaining_time":0.6161255965},
{"learn":[48.67732387],"iteration":717,"passed_time":1.562769869,"remaining_time":0.6137898371},
{"learn":[48.64651382],"iteration":718,"passed_time":1.564592726,"remaining_time":0.6114750433},
{"learn":[48.62420769],"iteration":719,"passed_time":1.566422245,"remaining_time":0.6091642065},
{"learn":[48.60152338],"iteration":720,"passed_time":1.569024015,"remaining_time":0.6071535371},
{"learn":[48.58529848],"iteration":721,"passed_time":1.572177328,"remaining_time":0.6053535972},
{"learn":[48.54532855],"iteration":722,"passed_time":1.574093313,"remaining_time":0.6030758612},
{"learn":[48.53792903],"iteration":723,"passed_time":1.575846354,"remaining_time":0.6007370078},
{"learn":[48.52946881],"iteration":724,"passed_time":1.577784326,"remaining_time":0.5984699167},
{"learn":[48.49421277],"iteration":725,"passed_time":1.579968394,"remaining_time":0.5962966113},
{"learn":[48.4717639],"iteration":726,"passed_time":1.582489992,"remaining_time":0.5942500245},
{"learn":[48.45185911],"iteration":727,"passed_time":1.584451187,"remaining_time":0.5919927512},
{"learn":[48.398459],"iteration":728,"passed_time":1.586330622,"remaining_time":0.5897058966},
{"learn":[48.35659621],"iteration":729,"passed_time":1.588214787,"remaining_time":0.5874219077},
{"learn":[48.34647437],"iteration":730,"passed_time":1.590072644,"remaining_time":0.5851293314},
{"learn":[48.33054049],"iteration":731,"passed_time":1.591875329,"remaining_time":0.5828177436},
{"learn":[48.30426179],"iteration":732,"passed_time":1.593750599,"remaining_time":0.5805339835},
{"learn":[48.28732441],"iteration":733,"passed_time":1.595577929,"remaining_time":0.5782339635},
{"learn":[48.28039656],"iteration":734,"passed_time":1.597462939,"remaining_time":0.5759560255},
{"learn":[48.24713053],"iteration":735,"passed_time":1.599359101,"remaining_time":0.5736831558},
{"learn":[48.21624087],"iteration":736,"passed_time":1.601217619,"remaining_time":0.5713978748},
{"learn":[48.17441072],"iteration":737,"passed_time":1.603942844,"remaining_time":0.5694214431},
{"learn":[48.13733044],"iteration":738,"passed_time":1.605763442,"remaining_time":0.567123489},
{"learn":[48.0822845],"iteration":739,"passed_time":1.607928932,"remaining_time":0.5649480033},
{"learn":[48.00347148],"iteration":740,"passed_time":1.60977959,"remaining_time":0.5626625018},
{"learn":[47.98957151],"iteration":741,"passed_time":1.611579437,"remaining_time":0.5603605051},
{"learn":[47.96843344],"iteration":742,"passed_time":1.613850297,"remaining_time":0.5582227811},
{"learn":[47.94778122],"iteration":743,"passed_time":1.615783501,"remaining_time":0.5559685166},
{"learn":[47.94060039],"iteration":744,"passed_time":1.618189081,"remaining_time":0.5538767997},
{"learn":[47.90428115],"iteration":745,"passed_time":1.620722082,"remaining_time":0.5518276257},
{"learn":[47.88747649],"iteration":746,"passed_time":1.623337115,"remaining_time":0.5498049398},
{"learn":[47.82781445],"iteration":747,"passed_time":1.625244369,"remaining_time":0.5475422206},
{"learn":[47.80649675],"iteration":748,"passed_time":1.626873163,"remaining_time":0.5451871346},
{"learn":[47.77579302],"iteration":749,"passed_time":1.628483108,"remaining_time":0.5428277025},
{"learn":[47.74341657],"iteration":750,"passed_time":1.63091389,"remaining_time":0.5407424216},
{"learn":[47.72470961],"iteration":751,"passed_time":1.634998898,"remaining_time":0.5392017641},
{"learn":[47.71073975],"iteration":752,"passed_time":1.637884251,"remaining_time":0.5372608366},
{"learn":[47.65307589],"iteration":753,"passed_time":1.639872697,"remaining_time":0.535024779},
{"learn":[47.58769432],"iteration":754,"passed_time":1.641686491,"remaining_time":0.5327327024},
{"learn":[47.56171402],"iteration":755,"passed_time":1.643639757,"remaining_time":0.5304869057},
{"learn":[47.5506961],"iteration":756,"passed_time":1.645540654,"remaining_time":0.5282250711},
{"learn":[47.52733287],"iteration":757,"passed_time":1.647382139,"remaining_time":0.5259452211},
{"learn":[47.51485318],"iteration":758,"passed_time":1.649160408,"remaining_time":0.5236464537},
{"learn":[47.48001746],"iteration":759,"passed_time":1.651014233,"remaining_time":0.5213729156},
{"learn":[47.45423536],"iteration":760,"passed_time":1.652817823,"remaining_time":0.5190847038},
{"learn":[47.43773713],"iteration":761,"passed_time":1.655839033,"remaining_time":0.5171780705},
{"learn":[47.38675192],"iteration":762,"passed_time":1.657683551,"remaining_time":0.5149030164},
{"learn":[47.37232818],"iteration":763,"passed_time":1.659403812,"remaining_time":0.5125907065},
{"learn":[47.36649854],"iteration":764,"passed_time":1.661155839,"remaining_time":0.5102897023},
{"learn":[47.33827093],"iteration":765,"passed_time":1.662918436,"remaining_time":0.5079933604},
{"learn":[47.29504607],"iteration":766,"passed_time":1.664799796,"remaining_time":0.5057344884},
{"learn":[47.28485337],"iteration":767,"passed_time":1.666729495,"remaining_time":0.5034912017},
{"learn":[47.2622219],"iteration":768,"passed_time":1.668434442,"remaining_time":0.5011812173},
{"learn":[47.19531751],"iteration":769,"passed_time":1.67033171,"remaining_time":0.4989302509},
{"learn":[47.17786463],"iteration":770,"passed_time":1.672088906,"remaining_time":0.4966385986},
{"learn":[47.15961339],"iteration":771,"passed_time":1.673991159,"remaining_time":0.4943911714},
{"learn":[47.155608],"iteration":772,"passed_time":1.677225538,"remaining_time":0.4925358306},
{"learn":[47.14020002],"iteration":773,"passed_time":1.679016897,"remaining_time":0.4902555796},
{"learn":[47.09941783],"iteration":774,"passed_time":1.680773877,"remaining_time":0.4879666094},
{"learn":[47.085481],"iteration":775,"passed_time":1.682550972,"remaining_time":0.4856848168},
{"learn":[47.05537659],"iteration":776,"passed_time":1.6844766,"remaining_time":0.4834469522},
{"learn":[47.02271416],"iteration":777,"passed_time":1.68720681,"remaining_time":0.4814394753},
{"learn":[46.95615272],"iteration":778,"passed_time":1.689036894,"remaining_time":0.47917478},
{"learn":[46.87812165],"iteration":779,"passed_time":1.690909586,"remaining_time":0.4769232166},
{"learn":[46.85853464],"iteration":780,"passed_time":1.692777014,"remaining_time":0.4746711473},
{"learn":[46.84123386],"iteration":781,"passed_time":1.694696059,"remaining_time":0.4724344512},
{"learn":[46.80673925],"iteration":782,"passed_time":1.697801512,"remaining_time":0.4705273666},
{"learn":[46.77944846],"iteration":783,"passed_time":1.699693836,"remaining_time":0.4682829956},
{"learn":[46.7587316],"iteration":784,"passed_time":1.70151294,"remaining_time":0.4660194675},
{"learn":[46.72724877],"iteration":785,"passed_time":1.703373574,"remaining_time":0.4637683777},
{"learn":[46.71211579],"iteration":786,"passed_time":1.705229885,"remaining_time":0.4615171099},
{"learn":[46.69293801],"iteration":787,"passed_time":1.707331146,"remaining_time":0.4593327449},
{"learn":[46.67680778],"iteration":788,"passed_time":1.709266496,"remaining_time":0.4571042213},
{"learn":[46.66242615],"iteration":789,"passed_time":1.711166061,"remaining_time":0.4548669277},
{"learn":[46.59895244],"iteration":790,"passed_time":1.7130568,"remaining_time":0.4526281559},
{"learn":[46.57952056],"iteration":791,"passed_time":1.715031919,"remaining_time":0.4504124232},
{"learn":[46.57047779],"iteration":792,"passed_time":1.716796667,"remaining_time":0.4481423833},
{"learn":[46.54115904],"iteration":793,"passed_time":1.719856085,"remaining_time":0.4462095132},
{"learn":[46.51436903],"iteration":794,"passed_time":1.721782022,"remaining_time":0.4439815278},
{"learn":[46.48344928],"iteration":795,"passed_time":1.72367381,"remaining_time":0.4417455494},
{"learn":[46.46373203],"iteration":796,"passed_time":1.72549386,"remaining_time":0.4394921626},
{"learn":[46.44860377],"iteration":797,"passed_time":1.727305214,"remaining_time":0.4372376608},
{"learn":[46.40245384],"iteration":798,"passed_time":1.729840912,"remaining_time":0.4351664872},
{"learn":[46.38283416],"iteration":799,"passed_time":1.731654006,"remaining_time":0.4329135015},
{"learn":[46.3542298],"iteration":800,"passed_time":1.733568368,"remaining_time":0.4306867731},
{"learn":[46.32716858],"iteration":801,"passed_time":1.735430782,"remaining_time":0.4284479984},
{"learn":[46.27997946],"iteration":802,"passed_time":1.737369436,"remaining_time":0.4262288654},
{"learn":[46.25425717],"iteration":803,"passed_time":1.739358444,"remaining_time":0.4240227053},
{"learn":[46.22639255],"iteration":804,"passed_time":1.743077664,"remaining_time":0.4222362043},
{"learn":[46.18948258],"iteration":805,"passed_time":1.74989021,"remaining_time":0.421189455},
{"learn":[46.16796709],"iteration":806,"passed_time":1.751756458,"remaining_time":0.4189454726},
{"learn":[46.14325093],"iteration":807,"passed_time":1.754006362,"remaining_time":0.416793591},
{"learn":[46.11402335],"iteration":808,"passed_time":1.756539047,"remaining_time":0.4147082299},
{"learn":[46.09803437],"iteration":809,"passed_time":1.758417408,"remaining_time":0.4124682809},
{"learn":[46.07057548],"iteration":810,"passed_time":1.760294787,"remaining_time":0.4102289947},
{"learn":[46.05259424],"iteration":811,"passed_time":1.763560241,"remaining_time":0.4083119771},
{"learn":[46.04160969],"iteration":812,"passed_time":1.765484223,"remaining_time":0.4060830869},
{"learn":[46.02182612],"iteration":813,"passed_time":1.767263452,"remaining_time":0.4038218699},
{"learn":[45.96471131],"iteration":814,"passed_time":1.769100692,"remaining_time":0.4015750038},
{"learn":[45.95831617],"iteration":815,"passed_time":1.770919501,"remaining_time":0.3993249855},
{"learn":[45.91431856],"iteration":816,"passed_time":1.773984154,"remaining_time":0.3973550799},
{"learn":[45.88632651],"iteration":817,"passed_time":1.775867807,"remaining_time":0.395119732},
{"learn":[45.87102481],"iteration":818,"passed_time":1.777683954,"remaining_time":0.3928703244},
{"learn":[45.84665344],"iteration":819,"passed_time":1.779548099,"remaining_time":0.3906325094},
{"learn":[45.8166087],"iteration":820,"passed_time":1.781519415,"remaining_time":0.3884189712},
{"learn":[45.8083003],"iteration":821,"passed_time":1.783571254,"remaining_time":0.386223459},
{"learn":[45.75510681],"iteration":822,"passed_time":1.785390717,"remaining_time":0.3839783195},
{"learn":[45.73444917],"iteration":823,"passed_time":1.787244079,"remaining_time":0.3817414537},
{"learn":[45.71613578],"iteration":824,"passed_time":1.788911522,"remaining_time":0.3794660804},
{"learn":[45.68745563],"iteration":825,"passed_time":1.790932279,"remaining_time":0.377266606},
{"learn":[45.66929506],"iteration":826,"passed_time":1.793129044,"remaining_time":0.3751043829},
{"learn":[45.62235182],"iteration":827,"passed_time":1.795435251,"remaining_time":0.3729648107},
{"learn":[45.58651524],"iteration":828,"passed_time":1.797281078,"remaining_time":0.3707298726},
{"learn":[45.55417955],"iteration":829,"passed_time":1.799114675,"remaining_time":0.3684933671},
{"learn":[45.5201753],"iteration":830,"passed_time":1.800933709,"remaining_time":0.3662548698},
{"learn":[45.49861742],"iteration":831,"passed_time":1.803078775,"remaining_time":0.3640832142},
{"learn":[45.44633803],"iteration":832,"passed_time":1.805993961,"remaining_time":0.3620660162},
{"learn":[45.41488474],"iteration":833,"passed_time":1.807755594,"remaining_time":0.3598170607},
{"learn":[45.37169262],"iteration":834,"passed_time":1.809538293,"remaining_time":0.3575734351},
{"learn":[45.35239072],"iteration":835,"passed_time":1.811358999,"remaining_time":0.3553383683},
{"learn":[45.3199059],"iteration":836,"passed_time":1.813480259,"remaining_time":0.3531628222},
{"learn":[45.28412064],"iteration":837,"passed_time":1.815300221,"remaining_time":0.3509291596},
{"learn":[45.23505781],"iteration":838,"passed_time":1.817159927,"remaining_time":0.3487041099},
{"learn":[45.20238784],"iteration":839,"passed_time":1.819019687,"remaining_time":0.3464799404},
{"learn":[45.17376016],"iteration":840,"passed_time":1.82105338,"remaining_time":0.3442895214},
{"learn":[45.1179282],"iteration":841,"passed_time":1.823024473,"remaining_time":0.3420877277},
{"learn":[45.0986683],"iteration":842,"passed_time":1.824895046,"remaining_time":0.3398677607},
{"learn":[45.07714501],"iteration":843,"passed_time":1.828224483,"remaining_time":0.3379182694},
{"learn":[45.04348997],"iteration":844,"passed_time":1.830271418,"remaining_time":0.3357302602},
{"learn":[45.01421055],"iteration":845,"passed_time":1.832821211,"remaining_time":0.3336341212},
{"learn":[44.97901896],"iteration":846,"passed_time":1.835486293,"remaining_time":0.3315577365},
{"learn":[44.92466711],"iteration":847,"passed_time":1.837417685,"remaining_time":0.329348453},
{"learn":[44.90314114],"iteration":848,"passed_time":1.839151583,"remaining_time":0.3271046985},
{"learn":[44.87334754],"iteration":849,"passed_time":1.840893079,"remaining_time":0.3248634846},
{"learn":[44.85987256],"iteration":850,"passed_time":1.843983213,"remaining_time":0.3228595754},
{"learn":[44.83951485],"iteration":851,"passed_time":1.845813388,"remaining_time":0.3206342505},
{"learn":[44.82054411],"iteration":852,"passed_time":1.847541888,"remaining_time":0.3183923301},
{"learn":[44.79891382],"iteration":853,"passed_time":1.850278501,"remaining_time":0.3163239591},
{"learn":[44.74456107],"iteration":854,"passed_time":1.852433106,"remaining_time":0.3141553221},
{"learn":[44.72217392],"iteration":855,"passed_time":1.854291795,"remaining_time":0.3119369376},
{"learn":[44.68882932],"iteration":856,"passed_time":1.856051934,"remaining_time":0.3097029481},
{"learn":[44.66651214],"iteration":857,"passed_time":1.857842315,"remaining_time":0.3074750685},
{"learn":[44.6433033],"iteration":858,"passed_time":1.860465534,"remaining_time":0.3053849131},
{"learn":[44.61817992],"iteration":859,"passed_time":1.862531081,"remaining_time":0.3032027341},
{"learn":[44.60499034],"iteration":860,"passed_time":1.864385375,"remaining_time":0.3009867214},
{"learn":[44.58853051],"iteration":861,"passed_time":1.866357932,"remaining_time":0.298790481},
{"learn":[44.58003493],"iteration":862,"passed_time":1.869054224,"remaining_time":0.2967096508},
{"learn":[44.53195444],"iteration":863,"passed_time":1.873692853,"remaining_time":0.2949331342},
{"learn":[44.53069357],"iteration":864,"passed_time":1.87718247,"remaining_time":0.2929706745},
{"learn":[44.49942288],"iteration":865,"passed_time":1.879006855,"remaining_time":0.2907470192},
{"learn":[44.46523465],"iteration":866,"passed_time":1.882048813,"remaining_time":0.2887110636},
{"learn":[44.43225423],"iteration":867,"passed_time":1.8838254,"remaining_time":0.2864803603},
{"learn":[44.42012401],"iteration":868,"passed_time":1.885785376,"remaining_time":0.2842783478},
{"learn":[44.40034247],"iteration":869,"passed_time":1.887663313,"remaining_time":0.282064633},
{"learn":[44.38461291],"iteration":870,"passed_time":1.889483307,"remaining_time":0.2798431074},
{"learn":[44.34447864],"iteration":871,"passed_time":1.891495949,"remaining_time":0.2776507815},
{"learn":[44.331648],"iteration":872,"passed_time":1.89325023,"remaining_time":0.275421282},
{"learn":[44.32210793],"iteration":873,"passed_time":1.894980147,"remaining_time":0.2731893575},
{"learn":[44.30144862],"iteration":874,"passed_time":1.896843044,"remaining_time":0.2709775777},
{"learn":[44.29083577],"iteration":875,"passed_time":1.898687617,"remaining_time":0.2687640006},
{"learn":[44.25508589],"iteration":876,"passed_time":1.90059092,"remaining_time":0.2665595019},
{"learn":[44.21673211],"iteration":877,"passed_time":1.902795915,"remaining_time":0.26439761},
{"learn":[44.20534042],"iteration":878,"passed_time":1.904824258,"remaining_time":0.2622113029},
{"learn":[44.19271838],"iteration":879,"passed_time":1.906668042,"remaining_time":0.2600001876},
{"learn":[44.16347835],"iteration":880,"passed_time":1.908467868,"remaining_time":0.2577839686},
{"learn":[44.14102423],"iteration":881,"passed_time":1.91038244,"remaining_time":0.2555840453},
{"learn":[44.13345776],"iteration":882,"passed_time":1.914716693,"remaining_time":0.2537053829},
{"learn":[44.11852244],"iteration":883,"passed_time":1.916653227,"remaining_time":0.2515065321},
{"learn":[44.09300711],"iteration":884,"passed_time":1.918411362,"remaining_time":0.2492850922},
{"learn":[44.06515907],"iteration":885,"passed_time":1.920452036,"remaining_time":0.247101052},
{"learn":[44.03293918],"iteration":886,"passed_time":1.922345581,"remaining_time":0.2448985915},
{"learn":[43.98547765],"iteration":887,"passed_time":1.924444185,"remaining_time":0.2427226901},
{"learn":[43.95272861],"iteration":888,"passed_time":1.926247088,"remaining_time":0.2405100414},
{"learn":[43.92666233],"iteration":889,"passed_time":1.928076873,"remaining_time":0.238301636},
{"learn":[43.88874882],"iteration":890,"passed_time":1.929890646,"remaining_time":0.2360921217},
{"learn":[43.87954535],"iteration":891,"passed_time":1.931708926,"remaining_time":0.2338840404},
{"learn":[43.84958647],"iteration":892,"passed_time":1.934213843,"remaining_time":0.2317591055},
{"learn":[43.82935708],"iteration":893,"passed_time":1.936082947,"remaining_time":0.2295579334},
{"learn":[43.80523547],"iteration":894,"passed_time":1.937956149,"remaining_time":0.2273579839},
{"learn":[43.77397396],"iteration":895,"passed_time":1.939786714,"remaining_time":0.225153815},
{"learn":[43.76113812],"iteration":896,"passed_time":1.941642648,"remaining_time":0.2229533921},
{"learn":[43.73480012],"iteration":897,"passed_time":1.943530174,"remaining_time":0.2207573248},
{"learn":[43.71388089],"iteration":898,"passed_time":1.945465802,"remaining_time":0.2185673481},
{"learn":[43.70712534],"iteration":899,"passed_time":1.947254401,"remaining_time":0.2163616002},
{"learn":[43.69072298],"iteration":900,"passed_time":1.949146905,"remaining_time":0.2141681949},
{"learn":[43.64713975],"iteration":901,"passed_time":1.951209688,"remaining_time":0.2119939572},
{"learn":[43.62664839],"iteration":902,"passed_time":1.953135203,"remaining_time":0.2098052212},
{"learn":[43.61367509],"iteration":903,"passed_time":1.956672808,"remaining_time":0.2077882627},
{"learn":[43.5922098],"iteration":904,"passed_time":1.958653261,"remaining_time":0.205604486},
{"learn":[43.5814039],"iteration":905,"passed_time":1.960481995,"remaining_time":0.2034054167},
{"learn":[43.55437455],"iteration":906,"passed_time":1.962332398,"remaining_time":0.2012093859},
{"learn":[43.53749982],"iteration":907,"passed_time":1.964243423,"remaining_time":0.1990202587},
{"learn":[43.52867674],"iteration":908,"passed_time":1.966980475,"remaining_time":0.196914437},
{"learn":[43.47657037],"iteration":909,"passed_time":1.968840719,"remaining_time":0.1947205107},
{"learn":[43.44900368],"iteration":910,"passed_time":1.970974684,"remaining_time":0.1925540581},
{"learn":[43.401081],"iteration":911,"passed_time":1.97274769,"remaining_time":0.1903528473},
{"learn":[43.38504072],"iteration":912,"passed_time":1.974498843,"remaining_time":0.1881504921},
{"learn":[43.38343017],"iteration":913,"passed_time":1.976396033,"remaining_time":0.1859628653},
{"learn":[43.35368091],"iteration":914,"passed_time":1.978384675,"remaining_time":0.1837843687},
{"learn":[43.35012033],"iteration":915,"passed_time":1.980831259,"remaining_time":0.1816482814},
{"learn":[43.32522433],"iteration":916,"passed_time":1.982708305,"remaining_time":0.1794599666},
{"learn":[43.30042963],"iteration":917,"passed_time":1.984566724,"remaining_time":0.177270666},
{"learn":[43.28326624],"iteration":918,"passed_time":1.986555392,"remaining_time":0.1750935655},
{"learn":[43.2611073],"iteration":919,"passed_time":1.988464627,"remaining_time":0.1729099675},
{"learn":[43.25278244],"iteration":920,"passed_time":1.99165616,"remaining_time":0.1708369562},
{"learn":[43.21451625],"iteration":921,"passed_time":2.000831013,"remaining_time":0.1692676996},
{"learn":[43.19258733],"iteration":922,"passed_time":2.0034568,"remaining_time":0.1671356161},
{"learn":[43.1670024],"iteration":923,"passed_time":2.005919015,"remaining_time":0.1649890099},
{"learn":[43.1231027],"iteration":924,"passed_time":2.008252684,"remaining_time":0.1628312987},
{"learn":[43.08265624],"iteration":925,"passed_time":2.011465092,"remaining_time":0.1607434307},
{"learn":[43.06702361],"iteration":926,"passed_time":2.013289238,"remaining_time":0.1585438127},
{"learn":[43.05390661],"iteration":927,"passed_time":2.015112523,"remaining_time":0.1563449372},
{"learn":[43.04862724],"iteration":928,"passed_time":2.016926509,"remaining_time":0.1541461595},
{"learn":[43.01606883],"iteration":929,"passed_time":2.018782863,"remaining_time":0.1519513983},
{"learn":[43.00137174],"iteration":930,"passed_time":2.021532967,"remaining_time":0.1498236034},
{"learn":[42.98358729],"iteration":931,"passed_time":2.024918757,"remaining_time":0.1477408535},
{"learn":[42.96866376],"iteration":932,"passed_time":2.026765549,"remaining_time":0.1455447929},
{"learn":[42.95605962],"iteration":933,"passed_time":2.028531755,"remaining_time":0.1433437857},
{"learn":[42.94835187],"iteration":934,"passed_time":2.03031834,"remaining_time":0.1411451252},
{"learn":[42.9245749],"iteration":935,"passed_time":2.033731448,"remaining_time":0.1390585606},
{"learn":[42.90535318],"iteration":936,"passed_time":2.035534932,"remaining_time":0.1368609399},
{"learn":[42.88932261],"iteration":937,"passed_time":2.037387644,"remaining_time":0.1346674136},
{"learn":[42.87099032],"iteration":938,"passed_time":2.039171316,"remaining_time":0.1324701281},
{"learn":[42.86492265],"iteration":939,"passed_time":2.040942331,"remaining_time":0.1302729147},
{"learn":[42.84568546],"iteration":940,"passed_time":2.044354146,"remaining_time":0.1281794842},
{"learn":[42.81714028],"iteration":941,"passed_time":2.046262734,"remaining_time":0.1259906991},
{"learn":[42.79661956],"iteration":942,"passed_time":2.048131084,"remaining_time":0.1238000762},
{"learn":[42.76043457],"iteration":943,"passed_time":2.050052497,"remaining_time":0.1216132837},
{"learn":[42.73385325],"iteration":944,"passed_time":2.051910777,"remaining_time":0.1194233785},
{"learn":[42.7152004],"iteration":945,"passed_time":2.054841465,"remaining_time":0.1172953902},
{"learn":[42.68627116],"iteration":946,"passed_time":2.056711222,"remaining_time":0.1151063303},
{"learn":[42.66193866],"iteration":947,"passed_time":2.058589596,"remaining_time":0.1129184166},
{"learn":[42.64357508],"iteration":948,"passed_time":2.060358906,"remaining_time":0.1107252942},
{"learn":[42.6349782],"iteration":949,"passed_time":2.062221639,"remaining_time":0.108537981},
{"learn":[42.61923534],"iteration":950,"passed_time":2.064047679,"remaining_time":0.1063494598},
{"learn":[42.61643871],"iteration":951,"passed_time":2.066180811,"remaining_time":0.1041771838},
{"learn":[42.57720905],"iteration":952,"passed_time":2.068098144,"remaining_time":0.1019943471},
{"learn":[42.56363786],"iteration":953,"passed_time":2.069972781,"remaining_time":0.09981000833},
{"learn":[42.52043641],"iteration":954,"passed_time":2.072175869,"remaining_time":0.09764179486},
{"learn":[42.49405226],"iteration":955,"passed_time":2.073919806,"remaining_time":0.09545237602},
{"learn":[42.47745021],"iteration":956,"passed_time":2.076351815,"remaining_time":0.09329480464},
{"learn":[42.46938922],"iteration":957,"passed_time":2.078164603,"remaining_time":0.09110951287},
{"learn":[42.46285946],"iteration":958,"passed_time":2.07995301,"remaining_time":0.0889239556},
{"learn":[42.44923226],"iteration":959,"passed_time":2.081807857,"remaining_time":0.08674199403},
{"learn":[42.42220099],"iteration":960,"passed_time":2.083681732,"remaining_time":0.08456148549},
{"learn":[42.38306599],"iteration":961,"passed_time":2.086006588,"remaining_time":0.08239942862},
{"learn":[42.35662019],"iteration":962,"passed_time":2.087896124,"remaining_time":0.08022030797},
{"learn":[42.33732046],"iteration":963,"passed_time":2.08980499,"remaining_time":0.07804250999},
{"learn":[42.30407593],"iteration":964,"passed_time":2.091966174,"remaining_time":0.0758744208},
{"learn":[42.29214066],"iteration":965,"passed_time":2.093708796,"remaining_time":0.07369161394},
{"learn":[42.2724919],"iteration":966,"passed_time":2.095463492,"remaining_time":0.07151012951},
{"learn":[42.23526893],"iteration":967,"passed_time":2.097438571,"remaining_time":0.06933681226},
{"learn":[42.2193914],"iteration":968,"passed_time":2.099294404,"remaining_time":0.06716008928},
{"learn":[42.19002892],"iteration":969,"passed_time":2.101184874,"remaining_time":0.0649850992},
{"learn":[42.16839616],"iteration":970,"passed_time":2.102989965,"remaining_time":0.0628081452},
{"learn":[42.15334632],"iteration":971,"passed_time":2.104803594,"remaining_time":0.0606322023},
{"learn":[42.13038678],"iteration":972,"passed_time":2.108073797,"remaining_time":0.05849742294},
{"learn":[42.10967644],"iteration":973,"passed_time":2.109887067,"remaining_time":0.05632142067},
{"learn":[42.08183148],"iteration":974,"passed_time":2.112262919,"remaining_time":0.05416058767},
{"learn":[42.05375835],"iteration":975,"passed_time":2.11412875,"remaining_time":0.05198677255},
{"learn":[42.03495432],"iteration":976,"passed_time":2.1173623,"remaining_time":0.04984578599},
{"learn":[42.02109123],"iteration":977,"passed_time":2.11924408,"remaining_time":0.04767215722},
{"learn":[41.99944451],"iteration":978,"passed_time":2.122355283,"remaining_time":0.04552549637},
{"learn":[41.97830032],"iteration":979,"passed_time":2.125756087,"remaining_time":0.04338277728},
{"learn":[41.95586215],"iteration":980,"passed_time":2.133166505,"remaining_time":0.04131515148},
{"learn":[41.94202088],"iteration":981,"passed_time":2.134887526,"remaining_time":0.0391323579},
{"learn":[41.87314532],"iteration":982,"passed_time":2.13666429,"remaining_time":0.03695146788},
{"learn":[41.83550676],"iteration":983,"passed_time":2.138444374,"remaining_time":0.03477145323},
{"learn":[41.82650089],"iteration":984,"passed_time":2.140265087,"remaining_time":0.03259286935},
{"learn":[41.77829123],"iteration":985,"passed_time":2.142536945,"remaining_time":0.03042141707},
{"learn":[41.76681817],"iteration":986,"passed_time":2.144398115,"remaining_time":0.02824435207},
{"learn":[41.76068646],"iteration":987,"passed_time":2.146337541,"remaining_time":0.02606887702},
{"learn":[41.74775579],"iteration":988,"passed_time":2.148098614,"remaining_time":0.02389189561},
{"learn":[41.71524354],"iteration":989,"passed_time":2.149918693,"remaining_time":0.02171635044},
{"learn":[41.64680512],"iteration":990,"passed_time":2.15304985,"remaining_time":0.01955342952},
{"learn":[41.59869469],"iteration":991,"passed_time":2.154916406,"remaining_time":0.01737835812},
{"learn":[41.57994138],"iteration":992,"passed_time":2.156662368,"remaining_time":0.01520305798},
{"learn":[41.56055586],"iteration":993,"passed_time":2.158469124,"remaining_time":0.01302898867},
{"learn":[41.52726252],"iteration":994,"passed_time":2.160268575,"remaining_time":0.01085562098},
{"learn":[41.50205897],"iteration":995,"passed_time":2.163318525,"remaining_time":0.008688026204},
{"learn":[41.46395562],"iteration":996,"passed_time":2.165026724,"remaining_time":0.006514624045},
{"learn":[41.45591742],"iteration":997,"passed_time":2.166862997,"remaining_time":0.004342410815},
{"learn":[41.44146939],"iteration":998,"passed_time":2.168556527,"remaining_time":0.002170727254},
{"learn":[41.41206183],"iteration":999,"passed_time":2.170487527,"remaining_time":0}
]}